Workbook

Sheet Customers
A1: customer_id | B1: first_name | C1: last_name | D1: email | E1: city | F1: state | G1: age | H1: gender | I1: join_date | J1: membership
A2: CUST-5001 | B2: Noah | C2: Brown | D2: user5001@email.com | E2: Phoenix | F2: AZ | G2: 25 | H2: Female | I2: 2022-04-16 | J2: Platinum
A3: CUST-5002 | B3: Sophia | C3: Wilson | D3: user5002@email.com | E3: San Jose | F3: CA | G3: 18 | H3: Female | I3: 2021-03-01 | J3: Gold
A4: CUST-5003 | B4: Sophia | C4: Miller | D4: user5003@email.com | E4: San Diego | F4: CA | G4: 29 | H4: Female | I4: 2021-04-11 | J4: Free
A5: CUST-5004 | B5: James | C5: Brown | D5: user5004@email.com | E5: Dallas | F5: TX | G5: 32 | H5: Male | I5: 2022-09-03 | J5: Free
A6: CUST-5005 | B6: Sophia | C6: Johnson | D6: user5005@email.com | E6: Houston | F6: TX | G6: 24 | H6: Male | I6: 2023-10-24 | J6: Free
A7: CUST-5006 | B7: James | C7: Johnson | D7: user5006@email.com | E7: Los Angeles | F7: CA | G7: 52 | H7: Male | I7: 2020-10-09 | J7: Free
A8: CUST-5007 | B8: Sophia | C8: Smith | D8: user5007@email.com | E8: Dallas | F8: TX | G8: 43 | H8: Male | I8: 2020-06-08 | J8: Silver
A9: CUST-5008 | B9: Emma | C9: Smith | D9: user5008@email.com | E9: San Antonio | F9: TX | G9: 21 | H9: Female | I9: 2021-07-21 | J9: Free
A10: CUST-5009 | B10: Ava | C10: Wilson | D10: user5009@email.com | E10: Philadelphia | F10: PA | G10: 54 | H10: Female | I10: 2023-02-02 | J10: Silver
A11: CUST-5010 | B11: Ava | C11: Wilson | D11: user5010@email.com | E11: Jacksonville | F11: FL | G11: 23 | H11: Male | I11: 2020-03-27 | J11: Free
A12: CUST-5011 | B12: Emma | C12: Smith | D12: user5011@email.com | E12: Philadelphia | F12: PA | G12: 48 | H12: Male | I12: 2023-10-25 | J12: Gold
A13: CUST-5012 | B13: Liam | C13: Davis | D13: user5012@email.com | E13: New York | F13: NY | G13: 25 | H13: Female | I13: 2020-04-16 | J13: Free
... A201: CUST-5200 | B201: Ava | C201: Garcia | D201: user5200@email.com | E201: Austin | F201: TX | G201: 64 | H201: Female | I201: 2021-12-20 | J201: Silver

Sheet Orders
A1: order_id | B1: customer_id | C1: order_date | D1: category | E1: product_name | F1: unit_price | G1: quantity | H1: discount_pct | I1: final_price | J1: order_total | K1: payment_method | L1: order_status | M1: rating
A2: ORD-20001 | B2: CUST-5001 | C2: 2024-02-27 | D2: Books | E2: Business Analytics | F2: 39.99 | G2: 1 | H2: 0 | I2: 39.99 | J2: 39.99 | K2: PayPal | L2: Delivered | M2: 4
A3: ORD-20002 | B3: CUST-5001 | C3: 2024-03-19 | D3: Toys | E3: Action Figure | F3: 19.99 | G3: 2 | H3: 0 | I3: 19.99 | J3: 39.98 | K3: Wallet | L3: Delivered | M3: 5
A4: ORD-20003 | B4: CUST-5001 | C4: 2022-01-05 | D4: Toys | E4: Puzzle 1000pcs | F4: 24.99 | G4: 2 | H4: 15 | I4: 21.24 | J4: 42.48 | K4: Wallet | L4: Delivered | M4: 5
A5: ORD-20004 | B5: CUST-5001 | C5: 2022-11-14 | D5: Home & Kitchen | E5: Blender | F5: 64.99 | G5: 3 | H5: 0 | I5: 64.99 | J5: 194.97 | K5: Credit Card | L5: Delivered
A6: ORD-20005 | B6: CUST-5001 | C6: 2024-07-01 | D6: Clothing | E6: Cotton T-Shirt | F6: 24.99 | G6: 4 | H6: 0 | I6: 24.99 | J6: 99.96 | K6: Credit Card | L6: Delivered | M6: 4
A7: ORD-20006 | B7: CUST-5001 | C7: 2023-05-11 | D7: Home & Kitchen | E7: Blender | F7: 64.99 | G7: 2 | H7: 5 | I7: 61.74 | J7: 123.48 | K7: UPI | L7: Delivered | M7: 5
A8: ORD-20007 | B8: CUST-5002 | C8: 2023-09-10 | D8: Home & Kitchen | E8: Blender | F8: 64.99 | G8: 1 | H8: 15 | I8: 55.24 | J8: 55.24 | K8: PayPal | L8: Delivered
A9: ORD-20008 | B9: CUST-5003 | C9: 2022-08-20 | D9: Sports | E9: Resistance Bands | F9: 19.99 | G9: 3 | H9: 0 | I9: 19.99 | J9: 59.97 | K9: Debit Card | L9: Delivered | M9: 5
A10: ORD-20009 | B10: CUST-5003 | C10: 2022-06-04 | D10: Electronics | E10: Bluetooth Speaker | F10: 49.99 | G10: 4 | H10: 5 | I10: 47.49 | J10: 189.96 | K10: UPI | L10: Delivered
A11: ORD-20010 | B11: CUST-5003 | C11: 2023-07-16 | D11: Sports | E11: Yoga Mat | F11: 29.99 | G11: 3 | H11: 15 | I11: 25.49 | J11: 76.47 | K11: UPI | L11: Delivered | M11: 4
A12: ORD-20011 | B12: CUST-5003 | C12: 2023-07-26 | D12: Sports | E12: Resistance Bands | F12: 19.99 | G12: 3 | H12: 0 | I12: 19.99 | J12: 59.97 | K12: UPI | L12: Delivered | M12: 5
A13: ORD-20012 | B13: CUST-5003 | C13: 2023-01-05 | D13: Toys | E13: Puzzle 1000pcs | F13: 24.99 | G13: 1 | H13: 10 | I13: 22.49 | J13: 22.49 | K13: PayPal | L13: Cancelled | M13: 3
A14: ORD-20013 | B14: CUST-5003 | C14: 2022-03-01 | D14: Home & Kitchen | E14: Coffee Maker | F14: 59.99 | G14: 4 | H14: 0 | I14: 59.99 | J14: 239.96 | K14: UPI | L14: Delivered | M14: 5
A15: ORD-20014 | B15: CUST-5003 | C15: 2022-06-24 | D15: Home & Kitchen | E15: Air Fryer | F15: 89.99 | G15: 1 | H15: 5 | I15: 85.49 | J15: 85.49 | K15: Wallet | L15: Delivered | M15: 5
A16: ORD-20015 | B16: CUST-5003 | C16: 2022-03-17 | D16: Electronics | E16: Smart Watch | F16: 199.99 | G16: 3 | H16: 10 | I16: 179.99 | J16: 539.97 | K16: Credit Card | L16: Delivered
A17: ORD-20016 | B17: CUST-5003 | C17: 2022-04-06 | D17: Electronics | E17: Wireless Earbuds | F17: 79.99 | G17: 1 | H17: 5 | I17: 75.99 | J17: 75.99 | K17: PayPal | L17: Delivered | M17: 5
A18: ORD-20017 | B18: CUST-5003 | C18: 2023-10-11 | D18: Sports | E18: Water Bottle | F18: 24.99 | G18: 3 | H18: 20 | I18: 19.99 | J18: 59.97 | K18: Wallet | L18: Delivered
A19: ORD-20018 | B19: CUST-5003 | C19: 2023-12-02 | D19: Beauty | E19: Lip Balm Set | F19: 14.99 | G19: 3 | H19: 5 | I19: 14.24 | J19: 42.72 | K19: Credit Card | L19: Delivered | M19: 4
A20: ORD-20019 | B20: CUST-5004 | C20: 2024-07-11 | D20: Home & Kitchen | E20: Non-stick Pan Set | F20: 44.99 | G20: 1 | H20: 20 | I20: 35.99 | J20: 35.99 | K20: PayPal | L20: Delivered | M20: 5
A21: ORD-20020 | B21: CUST-5004 | C21: 2023-01-23 | D21: Home & Kitchen | E21: Coffee Maker | F21: 59.99 | G21: 2 | H21: 0 | I21: 59.99 | J21: 119.98 | K21: Debit Card | L21: Delivered | M21: 5
A22: ORD-20021 | B22: CUST-5004 | C22: 2022-03-22 | D22: Home & Kitchen | E22: Non-stick Pan Set | F22: 44.99 | G22: 4 | H22: 15 | I22: 38.24 | J22: 152.96 | K22: Credit Card | L22: Delivered | M22: 5
A23: ORD-20022 | B23: CUST-5004 | C23: 2024-09-19 | D23: Beauty | E23: Hair Mask | F23: 24.99 | G23: 4 | H23: 0 | I23: 24.99 | J23: 99.96 | K23: Credit Card | L23: Delivered | M23: 1
A24: ORD-20023 | B24: CUST-5004 | C24: 2024-03-16 | D24: Clothing | E24: Running Shoes | F24: 89.99 | G24: 2 | H24: 10 | I24: 80.99 | J24: 161.98 | K24: UPI | L24: Delivered | M24: 4
A25: ORD-20024 | B25: CUST-5004 | C25: 2024-11-07 | D25: Books | E25: Fiction Novel | F25: 14.99 | G25: 1 | H25: 10 | I25: 13.49 | J25: 13.49 | K25: Credit Card | L25: Delivered | M25: 5
A26: ORD-20025 | B26: CUST-5004 | C26: 2023-01-20 | D26: Beauty | E26: Face Serum | F26: 39.99 | G26: 4 | H26: 10 | I26: 35.99 | J26: 143.96 | K26: Wallet | L26: Delivered
A27: ORD-20026 | B27: CUST-5004 | C27: 2024-03-13 | D27: Beauty | E27: Hair Mask | F27: 24.99 | G27: 2 | H27: 15 | I27: 21.24 | J27: 42.48 | K27: Wallet | L27: Delivered | M27: 4
A28: ORD-20027 | B28: CUST-5004 | C28: 2022-02-27 | D28: Clothing | E28: Yoga Pants | F28: 44.99 | G28: 2 | H28: 5 | I28: 42.74 | J28: 85.48 | K28: UPI | L28: Delivered | M28: 3
A29: ORD-20028 | B29: CUST-5004 | C29: 2022-03-01 | D29: Clothing | E29: Yoga Pants | F29: 44.99 | G29: 1 | H29: 0 | I29: 44.99 | J29: 44.99 | K29: Debit Card | L29: Delivered | M29: 5
A30: ORD-20029 | B30: CUST-5004 | C30: 2023-04-12 | D30: Beauty | E30: Face Serum | F30: 39.99 | G30: 3 | H30: 20 | I30: 31.99 | J30: 95.97 | K30: Credit Card | L30: Processing
A31: ORD-20030 | B31: CUST-5004 | C31: 2023-06-16 | D31: Electronics | E31: Smart Watch | F31: 199.99 | G31: 4 | H31: 20 | I31: 159.99 | J31: 639.96 | K31: UPI | L31: Delivered | M31: 5
A32: ORD-20031 | B32: CUST-5004 | C32: 2022-10-06 | D32: Toys | E32: Action Figure | F32: 19.99 | G32: 4 | H32: 0 | I32: 19.99 | J32: 79.96 | K32: Debit Card | L32: Delivered | M32: 5
A33: ORD-20032 | B33: CUST-5005 | C33: 2023-10-10 | D33: Beauty | E33: Moisturizer SPF 50 | F33: 29.99 | G33: 3 | H33: 20 | I33: 23.99 | J33: 71.97 | K33: Wallet | L33: Delivered
A34: ORD-20033 | B34: CUST-5005 | C34: 2024-10-10 | D34: Clothing | E34: Running Shoes | F34: 89.99 | G34: 1 | H34: 0 | I34: 89.99 | J34: 89.99 | K34: UPI | L34: Delivered | M34: 5
A35: ORD-20034 | B35: CUST-5005 | C35: 2022-09-11 | D35: Sports | E35: Jump Rope | F35: 14.99 | G35: 2 | H35: 0 | I35: 14.99 | J35: 29.98 | K35: Credit Card | L35: Delivered | M35: 3
A36: ORD-20035 | B36: CUST-5005 | C36: 2022-11-13 | D36: Books | E36: Fiction Novel | F36: 14.99 | G36: 1 | H36: 15 | I36: 12.74 | J36: 12.74 | K36: UPI | L36: Delivered | M36: 5
A37: ORD-20036 | B37: CUST-5005 | C37: 2023-10-21 | D37: Beauty | E37: Moisturizer SPF 50 | F37: 29.99 | G37: 1 | H37: 20 | I37: 23.99 | J37: 23.99 | K37: PayPal | L37: Delivered | M37: 3
A38: ORD-20037 | B38: CUST-5005 | C38: 2024-10-14 | D38: Home & Kitchen | E38: Air Fryer | F38: 89.99 | G38: 2 | H38: 20 | I38: 71.99 | J38: 143.98 | K38: Debit Card | L38: Delivered | M38: 5
A39: ORD-20038 | B39: CUST-5005 | C39: 2023-01-13 | D39: Electronics | E39: Bluetooth Speaker | F39: 49.99 | G39: 1 | H39: 15 | I39: 42.49 | J39: 42.49 | K39: Wallet | L39: Delivered
A40: ORD-20039 | B40: CUST-5005 | C40: 2023-03-24 | D40: Electronics | E40: Wireless Earbuds | F40: 79.99 | G40: 3 | H40: 5 | I40: 75.99 | J40: 227.97 | K40: Wallet | L40: Delivered | M40: 5
A41: ORD-20040 | B41: CUST-5005 | C41: 2023-08-18 | D41: Toys | E41: LEGO Classic Set | F41: 49.99 | G41: 3 | H41: 20 | I41: 39.99 | J41: 119.97 | K41: UPI | L41: Delivered
A42: ORD-20041 | B42: CUST-5006 | C42: 2022-03-18 | D42: Sports | E42: Resistance Bands | F42: 19.99 | G42: 1 | H42: 15 | I42: 16.99 | J42: 16.99 | K42: Debit Card | L42: Delivered | M42: 4
A43: ORD-20042 | B43: CUST-5006 | C43: 2024-07-10 | D43: Clothing | E43: Cotton T-Shirt | F43: 24.99 | G43: 4 | H43: 0 | I43: 24.99 | J43: 99.96 | K43: Credit Card | L43: Delivered
A44: ORD-20043 | B44: CUST-5006 | C44: 2024-01-03 | D44: Books | E44: Data Science Handbook | F44: 49.99 | G44: 1 | H44: 0 | I44: 49.99 | J44: 49.99 | K44: Wallet | L44: Delivered | M44: 4
A45: ORD-20044 | B45: CUST-5006 | C45: 2022-08-27 | D45: Books | E45: Business Analytics | F45: 39.99 | G45: 4 | H45: 15 | I45: 33.99 | J45: 135.96 | K45: Debit Card | L45: Delivered | M45: 5
A46: ORD-20045 | B46: CUST-5006 | C46: 2022-06-23 | D46: Sports | E46: Jump Rope | F46: 14.99 | G46: 2 | H46: 15 | I46: 12.74 | J46: 25.48 | K46: Credit Card | L46: Delivered | M46: 5
A47: ORD-20046 | B47: CUST-5006 | C47: 2024-08-26 | D47: Home & Kitchen | E47: Air Fryer | F47: 89.99 | G47: 1 | H47: 15 | I47: 76.49 | J47: 76.49 | K47: Debit Card | L47: Processing | M47: 5
A48: ORD-20047 | B48: CUST-5006 | C48: 2022-08-19 | D48: Toys | E48: Action Figure | F48: 19.99 | G48: 4 | H48: 0 | I48: 19.99 | J48: 79.96 | K48: Debit Card | L48: Delivered | M48: 5
A49: ORD-20048 | B49: CUST-5006 | C49: 2023-03-18 | D49: Home & Kitchen | E49: Coffee Maker | F49: 59.99 | G49: 4 | H49: 0 | I49: 59.99 | J49: 239.96 | K49: UPI | L49: Delivered | M49: 3
A50: ORD-20049 | B50: CUST-5006 | C50: 2022-06-11 | D50: Sports | E50: Yoga Mat | F50: 29.99 | G50: 4 | H50: 0 | I50: 29.99 | J50: 119.96 | K50: PayPal | L50: Delivered | M50: 3
A51: ORD-20050 | B51: CUST-5006 | C51: 2022-02-27 | D51: Home & Kitchen | E51: Non-stick Pan Set | F51: 44.99 | G51: 2 | H51: 0 | I51: 44.99 | J51: 89.98 | K51: Debit Card | L51: Delivered
A52: ORD-20051 | B52: CUST-5006 | C52: 2023-05-24 | D52: Home & Kitchen | E52: Air Fryer | F52: 89.99 | G52: 1 | H52: 0 | I52: 89.99 | J52: 89.99 | K52: Credit Card | L52: Returned
A53: ORD-20052 | B53: CUST-5006 | C53: 2023-07-24 | D53: Sports | E53: Jump Rope | F53: 14.99 | G53: 2 | H53: 5 | I53: 14.24 | J53: 28.48 | K53: Wallet | L53: Shipped | M53: 5
A54: ORD-20053 | B54: CUST-5006 | C54: 2024-04-07 | D54: Beauty | E54: Moisturizer SPF 50 | F54: 29.99 | G54: 2 | H54: 10 | I54: 26.99 | J54: 53.98 | K54: PayPal | L54: Delivered
A55: ORD-20054 | B55: CUST-5007 | C55: 2022-03-19 | D55: Sports | E55: Water Bottle | F55: 24.99 | G55: 2 | H55: 0 | I55: 24.99 | J55: 49.98 | K55: Wallet | L55: Delivered
A56: ORD-20055 | B56: CUST-5007 | C56: 2024-04-05 | D56: Sports | E56: Resistance Bands | F56: 19.99 | G56: 2 | H56: 0 | I56: 19.99 | J56: 39.98 | K56: Debit Card | L56: Delivered | M56: 5
A57: ORD-20056 | B57: CUST-5007 | C57: 2023-12-12 | D57: Sports | E57: Water Bottle | F57: 24.99 | G57: 3 | H57: 20 | I57: 19.99 | J57: 59.97 | K57: UPI | L57: Delivered
A58: ORD-20057 | B58: CUST-5007 | C58: 2022-12-08 | D58: Clothing | E58: Yoga Pants | F58: 44.99 | G58: 4 | H58: 20 | I58: 35.99 | J58: 143.96 | K58: UPI | L58: Delivered
A59: ORD-20058 | B59: CUST-5007 | C59: 2023-06-23 | D59: Home & Kitchen | E59: Air Fryer | F59: 89.99 | G59: 4 | H59: 0 | I59: 89.99 | J59: 359.96 | K59: Debit Card | L59: Shipped | M59: 5
A60: ORD-20059 | B60: CUST-5007 | C60: 2022-02-15 | D60: Clothing | E60: Denim Jacket | F60: 69.99 | G60: 2 | H60: 20 | I60: 55.99 | J60: 111.98 | K60: Credit Card | L60: Delivered
A61: ORD-20060 | B61: CUST-5007 | C61: 2022-04-19 | D61: Books | E61: Fiction Novel | F61: 14.99 | G61: 1 | H61: 10 | I61: 13.49 | J61: 13.49 | K61: Wallet | L61: Delivered | M61: 5
A62: ORD-20061 | B62: CUST-5007 | C62: 2024-11-10 | D62: Beauty | E62: Hair Mask | F62: 24.99 | G62: 4 | H62: 15 | I62: 21.24 | J62: 84.96 | K62: Credit Card | L62: Delivered
A63: ORD-20062 | B63: CUST-5007 | C63: 2023-07-11 | D63: Sports | E63: Jump Rope | F63: 14.99 | G63: 2 | H63: 20 | I63: 11.99 | J63: 23.98 | K63: Debit Card | L63: Delivered | M63: 4
A64: ORD-20063 | B64: CUST-5007 | C64: 2022-02-18 | D64: Beauty | E64: Moisturizer SPF 50 | F64: 29.99 | G64: 2 | H64: 0 | I64: 29.99 | J64: 59.98 | K64: Debit Card | L64: Delivered | M64: 5
A65: ORD-20064 | B65: CUST-5007 | C65: 2024-04-12 | D65: Toys | E65: Action Figure | F65: 19.99 | G65: 2 | H65: 10 | I65: 17.99 | J65: 35.98 | K65: Credit Card | L65: Delivered | M65: 3
A66: ORD-20065 | B66: CUST-5008 | C66: 2022-10-27 | D66: Electronics | E66: USB-C Hub | F66: 34.99 | G66: 3 | H66: 15 | I66: 29.74 | J66: 89.22 | K66: Credit Card | L66: Delivered
A67: ORD-20066 | B67: CUST-5008 | C67: 2023-08-06 | D67: Electronics | E67: Smart Watch | F67: 199.99 | G67: 4 | H67: 0 | I67: 199.99 | J67: 799.96 | K67: Wallet | L67: Delivered | M67: 5
A68: ORD-20067 | B68: CUST-5008 | C68: 2022-03-09 | D68: Toys | E68: Remote Control Car | F68: 39.99 | G68: 4 | H68: 5 | I68: 37.99 | J68: 151.96 | K68: PayPal | L68: Delivered | M68: 5
A69: ORD-20068 | B69: CUST-5008 | C69: 2023-08-02 | D69: Home & Kitchen | E69: Blender | F69: 64.99 | G69: 3 | H69: 0 | I69: 64.99 | J69: 194.97 | K69: PayPal | L69: Delivered | M69: 5
A70: ORD-20069 | B70: CUST-5008 | C70: 2023-11-06 | D70: Toys | E70: Remote Control Car | F70: 39.99 | G70: 4 | H70: 0 | I70: 39.99 | J70: 159.96 | K70: Debit Card | L70: Delivered | M70: 4
A71: ORD-20070 | B71: CUST-5008 | C71: 2024-05-01 | D71: Books | E71: Business Analytics | F71: 39.99 | G71: 3 | H71: 5 | I71: 37.99 | J71: 113.97 | K71: Credit Card | L71: Delivered
A72: ORD-20071 | B72: CUST-5008 | C72: 2022-12-06 | D72: Books | E72: Python for Beginners | F72: 29.99 | G72: 3 | H72: 0 | I72: 29.99 | J72: 89.97 | K72: UPI | L72: Delivered | M72: 5
A73: ORD-20072 | B73: CUST-5008 | C73: 2022-11-13 | D73: Books | E73: Python for Beginners | F73: 29.99 | G73: 3 | H73: 0 | I73: 29.99 | J73: 89.97 | K73: UPI | L73: Delivered
A74: ORD-20073 | B74: CUST-5009 | C74: 2022-05-25 | D74: Toys | E74: Puzzle 1000pcs | F74: 24.99 | G74: 1 | H74: 15 | I74: 21.24 | J74: 21.24 | K74: Debit Card | L74: Delivered | M74: 4
A75: ORD-20074 | B75: CUST-5009 | C75: 2023-03-20 | D75: Beauty | E75: Lip Balm Set | F75: 14.99 | G75: 4 | H75: 20 | I75: 11.99 | J75: 47.96 | K75: Wallet | L75: Delivered | M75: 4
A76: ORD-20075 | B76: CUST-5009 | C76: 2023-04-04 | D76: Toys | E76: Action Figure | F76: 19.99 | G76: 1 | H76: 15 | I76: 16.99 | J76: 16.99 | K76: UPI | L76: Delivered | M76: 4
A77: ORD-20076 | B77: CUST-5009 | C77: 2024-01-20 | D77: Toys | E77: Remote Control Car | F77: 39.99 | G77: 4 | H77: 20 | I77: 31.99 | J77: 127.96 | K77: UPI | L77: Shipped | M77: 5
A78: ORD-20077 | B78: CUST-5009 | C78: 2023-06-22 | D78: Home & Kitchen | E78: Blender | F78: 64.99 | G78: 1 | H78: 0 | I78: 64.99 | J78: 64.99 | K78: PayPal | L78: Returned | M78: 4
A79: ORD-20078 | B79: CUST-5009 | C79: 2022-02-13 | D79: Beauty | E79: Hair Mask | F79: 24.99 | G79: 2 | H79: 0 | I79: 24.99 | J79: 49.98 | K79: UPI | L79: Delivered | M79: 5
A80: ORD-20079 | B80: CUST-5009 | C80: 2023-07-24 | D80: Toys | E80: LEGO Classic Set | F80: 49.99 | G80: 3 | H80: 0 | I80: 49.99 | J80: 149.97 | K80: Wallet | L80: Delivered | M80: 5
A81: ORD-20080 | B81: CUST-5009 | C81: 2023-06-27 | D81: Electronics | E81: USB-C Hub | F81: 34.99 | G81: 2 | H81: 0 | I81: 34.99 | J81: 69.98 | K81: PayPal | L81: Delivered | M81: 3
A82: ORD-20081 | B82: CUST-5009 | C82: 2022-04-13 | D82: Home & Kitchen | E82: Coffee Maker | F82: 59.99 | G82: 1 | H82: 15 | I82: 50.99 | J82: 50.99 | K82: Wallet | L82: Delivered | M82: 4
A83: ORD-20082 | B83: CUST-5009 | C83: 2024-11-17 | D83: Beauty | E83: Hair Mask | F83: 24.99 | G83: 3 | H83: 20 | I83: 19.99 | J83: 59.97 | K83: UPI | L83: Delivered | M83: 5
A84: ORD-20083 | B84: CUST-5009 | C84: 2023-04-02 | D84: Home & Kitchen | E84: Air Fryer | F84: 89.99 | G84: 3 | H84: 5 | I84: 85.49 | J84: 256.47 | K84: UPI | L84: Delivered | M84: 5
A85: ORD-20084 | B85: CUST-5009 | C85: 2024-07-18 | D85: Clothing | E85: Running Shoes | F85: 89.99 | G85: 3 | H85: 5 | I85: 85.49 | J85: 256.47 | K85: PayPal | L85: Delivered | M85: 5
A86: ORD-20085 | B86: CUST-5009 | C86: 2022-12-19 | D86: Books | E86: Business Analytics | F86: 39.99 | G86: 4 | H86: 0 | I86: 39.99 | J86: 159.96 | K86: Credit Card | L86: Delivered
A87: ORD-20086 | B87: CUST-5009 | C87: 2024-05-12 | D87: Electronics | E87: Smart Watch | F87: 199.99 | G87: 4 | H87: 10 | I87: 179.99 | J87: 719.96 | K87: Debit Card | L87: Delivered | M87: 4
A88: ORD-20087 | B88: CUST-5010 | C88: 2022-05-19 | D88: Books | E88: Python for Beginners | F88: 29.99 | G88: 1 | H88: 20 | I88: 23.99 | J88: 23.99 | K88: Debit Card | L88: Delivered | M88: 5
A89: ORD-20088 | B89: CUST-5010 | C89: 2024-10-13 | D89: Home & Kitchen | E89: Air Fryer | F89: 89.99 | G89: 3 | H89: 0 | I89: 89.99 | J89: 269.97 | K89: PayPal | L89: Delivered | M89: 3
A90: ORD-20089 | B90: CUST-5010 | C90: 2022-10-01 | D90: Electronics | E90: Bluetooth Speaker | F90: 49.99 | G90: 2 | H90: 5 | I90: 47.49 | J90: 94.98 | K90: UPI | L90: Delivered | M90: 2
A91: ORD-20090 | B91: CUST-5010 | C91: 2023-05-17 | D91: Beauty | E91: Moisturizer SPF 50 | F91: 29.99 | G91: 3 | H91: 0 | I91: 29.99 | J91: 89.97 | K91: PayPal | L91: Delivered | M91: 3
A92: ORD-20091 | B92: CUST-5010 | C92: 2023-01-16 | D92: Toys | E92: Action Figure | F92: 19.99 | G92: 2 | H92: 5 | I92: 18.99 | J92: 37.98 | K92: PayPal | L92: Delivered | M92: 4
A93: ORD-20092 | B93: CUST-5010 | C93: 2023-05-15 | D93: Toys | E93: Action Figure | F93: 19.99 | G93: 4 | H93: 10 | I93: 17.99 | J93: 71.96 | K93: PayPal | L93: Delivered | M93: 5
A94: ORD-20093 | B94: CUST-5011 | C94: 2024-09-18 | D94: Beauty | E94: Moisturizer SPF 50 | F94: 29.99 | G94: 2 | H94: 5 | I94: 28.49 | J94: 56.98 | K94: Credit Card | L94: Delivered | M94: 4
A95: ORD-20094 | B95: CUST-5011 | C95: 2024-12-09 | D95: Beauty | E95: Moisturizer SPF 50 | F95: 29.99 | G95: 3 | H95: 0 | I95: 29.99 | J95: 89.97 | K95: PayPal | L95: Delivered | M95: 3
A96: ORD-20095 | B96: CUST-5011 | C96: 2023-09-20 | D96: Home & Kitchen | E96: Non-stick Pan Set | F96: 44.99 | G96: 2 | H96: 15 | I96: 38.24 | J96: 76.48 | K96: PayPal | L96: Delivered | M96: 3
A97: ORD-20096 | B97: CUST-5011 | C97: 2022-07-14 | D97: Sports | E97: Water Bottle | F97: 24.99 | G97: 3 | H97: 20 | I97: 19.99 | J97: 59.97 | K97: Wallet | L97: Delivered | M97: 3
A98: ORD-20097 | B98: CUST-5012 | C98: 2023-07-21 | D98: Sports | E98: Yoga Mat | F98: 29.99 | G98: 2 | H98: 10 | I98: 26.99 | J98: 53.98 | K98: Wallet | L98: Delivered | M98: 4
... A102: ORD-20101 | B102: CUST-5012 | C102: 2022-08-06 | D102: Home & Kitchen | E102: Non-stick Pan Set | F102: 44.99 | G102: 3 | H102: 0 | I102: 44.99 | J102: 134.97 | K102: UPI | L102: Delivered | M102: 5
A103: ORD-20102 | B103: CUST-5012 | C103: 2023-09-28 | D103: Clothing | E103: Denim Jacket | F103: 69.99 | G103: 1 | H103: 0 | I103: 69.99 | J103: 69.99 | K103: Wallet | L103: Delivered
...

Sheet Master
A1: order_id | B1: customer_id | C1: order_date | D1: category | E1: product_name | F1: unit_price | G1: quantity | H1: discount_pct | I1: final_price | J1: order_total | K1: payment_method | L1: order_status | M1: rating | N1: Customer Age | O1: Customer City | P1: Membership | Q1: Gender | R1: Date_Check | S1: Month_Start
A2: ORD-20001 | B2: CUST-5001 | C2: 45349 | D2: Books | E2: Business Analytics | F2: 39.99 | G2: 1 | H2: 0 | I2: 39.99 | J2: 39.99 | K2: PayPal | L2: Delivered | M2: 4 | N2: =VLOOKUP(B2,Customers!A:J,7,0) -> 25 | O2: =VLOOKUP(B2,Customers!A:J,5,0) -> Phoenix | P2: =VLOOKUP(B2,Customers!A:J,10,0) -> Platinum | Q2: =VLOOKUP(B2,Customers!A:J,8,0) -> Female | R2: =ISNUMBER(C2) -> TRUE | S2: =DATE(YEAR(C2),MONTH(C2),1) -> 45323
A3: ORD-20002 | B3: CUST-5001 | C3: 45370 | D3: Toys | E3: Action Figure | F3: 19.99 | G3: 2 | H3: 0 | I3: 19.99 | J3: 39.98 | K3: Wallet | L3: Delivered | M3: 5 | N3: =VLOOKUP(B3,Customers!A:J,7,0) -> 25 | O3: =VLOOKUP(B3,Customers!A:J,5,0) -> Phoenix | P3: =VLOOKUP(B3,Customers!A:J,10,0) -> Platinum | Q3: =VLOOKUP(B3,Customers!A:J,8,0) -> Female | R3: =ISNUMBER(C3) -> TRUE | S3: =DATE(YEAR(C3),MONTH(C3),1) -> 45352
A4: ORD-20003 | B4: CUST-5001 | C4: 44566 | D4: Toys | E4: Puzzle 1000pcs | F4: 24.99 | G4: 2 | H4: 15 | I4: 21.24 | J4: 42.48 | K4: Wallet | L4: Delivered | M4: 5 | N4: =VLOOKUP(B4,Customers!A:J,7,0) -> 25 | O4: =VLOOKUP(B4,Customers!A:J,5,0) -> Phoenix | P4: =VLOOKUP(B4,Customers!A:J,10,0) -> Platinum | Q4: =VLOOKUP(B4,Customers!A:J,8,0) -> Female | R4: =ISNUMBER(C4) -> TRUE | S4: =DATE(YEAR(C4),MONTH(C4),1) -> 44562
A5: ORD-20004 | B5: CUST-5001 | C5: 44879 | D5: Home & Kitchen | E5: Blender | F5: 64.99 | G5: 3 | H5: 0 | I5: 64.99 | J5: 194.97 | K5: Credit Card | L5: Delivered | N5: =VLOOKUP(B5,Customers!A:J,7,0) -> 25 | O5: =VLOOKUP(B5,Customers!A:J,5,0) -> Phoenix | P5: =VLOOKUP(B5,Customers!A:J,10,0) -> Platinum | Q5: =VLOOKUP(B5,Customers!A:J,8,0) -> Female | R5: =ISNUMBER(C5) -> TRUE | S5: =DATE(YEAR(C5),MONTH(C5),1) -> 44866
A6: ORD-20005 | B6: CUST-5001 | C6: 45474 | D6: Clothing | E6: Cotton T-Shirt | F6: 24.99 | G6: 4 | H6: 0 | I6: 24.99 | J6: 99.96 | K6: Credit Card | L6: Delivered | M6: 4 | N6: =VLOOKUP(B6,Customers!A:J,7,0) -> 25 | O6: =VLOOKUP(B6,Customers!A:J,5,0) -> Phoenix | P6: =VLOOKUP(B6,Customers!A:J,10,0) -> Platinum | Q6: =VLOOKUP(B6,Customers!A:J,8,0) -> Female | R6: =ISNUMBER(C6) -> TRUE | S6: =DATE(YEAR(C6),MONTH(C6),1) -> 45474
A7: ORD-20006 | B7: CUST-5001 | C7: 45057 | D7: Home & Kitchen | E7: Blender | F7: 64.99 | G7: 2 | H7: 5 | I7: 61.74 | J7: 123.48 | K7: UPI | L7: Delivered | M7: 5 | N7: =VLOOKUP(B7,Customers!A:J,7,0) -> 25 | O7: =VLOOKUP(B7,Customers!A:J,5,0) -> Phoenix | P7: =VLOOKUP(B7,Customers!A:J,10,0) -> Platinum | Q7: =VLOOKUP(B7,Customers!A:J,8,0) -> Female | R7: =ISNUMBER(C7) -> TRUE | S7: =DATE(YEAR(C7),MONTH(C7),1) -> 45047
A8: ORD-20007 | B8: CUST-5002 | C8: 45179 | D8: Home & Kitchen | E8: Blender | F8: 64.99 | G8: 1 | H8: 15 | I8: 55.24 | J8: 55.24 | K8: PayPal | L8: Delivered | N8: =VLOOKUP(B8,Customers!A:J,7,0) -> 18 | O8: =VLOOKUP(B8,Customers!A:J,5,0) -> San Jose | P8: =VLOOKUP(B8,Customers!A:J,10,0) -> Gold | Q8: =VLOOKUP(B8,Customers!A:J,8,0) -> Female | R8: =ISNUMBER(C8) -> TRUE | S8: =DATE(YEAR(C8),MONTH(C8),1) -> 45170
A9: ORD-20008 | B9: CUST-5003 | C9: 44793 | D9: Sports | E9: Resistance Bands | F9: 19.99 | G9: 3 | H9: 0 | I9: 19.99 | J9: 59.97 | K9: Debit Card | L9: Delivered | M9: 5 | N9: =VLOOKUP(B9,Customers!A:J,7,0) -> 29 | O9: =VLOOKUP(B9,Customers!A:J,5,0) -> San Diego | P9: =VLOOKUP(B9,Customers!A:J,10,0) -> Free | Q9: =VLOOKUP(B9,Customers!A:J,8,0) -> Female | R9: =ISNUMBER(C9) -> TRUE | S9: =DATE(YEAR(C9),MONTH(C9),1) -> 44774
A10: ORD-20009 | B10: CUST-5003 | C10: 44716 | D10: Electronics | E10: Bluetooth Speaker | F10: 49.99 | G10: 4 | H10: 5 | I10: 47.49 | J10: 189.96 | K10: UPI | L10: Delivered | N10: =VLOOKUP(B10,Customers!A:J,7,0) -> 29 | O10: =VLOOKUP(B10,Customers!A:J,5,0) -> San Diego | P10: =VLOOKUP(B10,Customers!A:J,10,0) -> Free | Q10: =VLOOKUP(B10,Customers!A:J,8,0) -> Female | R10: =ISNUMBER(C10) -> TRUE | S10: =DATE(YEAR(C10),MONTH(C10),1) -> 44713
A11: ORD-20010 | B11: CUST-5003 | C11: 45123 | D11: Sports | E11: Yoga Mat | F11: 29.99 | G11: 3 | H11: 15 | I11: 25.49 | J11: 76.47 | K11: UPI | L11: Delivered | M11: 4 | N11: =VLOOKUP(B11,Customers!A:J,7,0) -> 29 | O11: =VLOOKUP(B11,Customers!A:J,5,0) -> San Diego | P11: =VLOOKUP(B11,Customers!A:J,10,0) -> Free | Q11: =VLOOKUP(B11,Customers!A:J,8,0) -> Female | R11: =ISNUMBER(C11) -> TRUE | S11: =DATE(YEAR(C11),MONTH(C11),1) -> 45108
A12: ORD-20011 | B12: CUST-5003 | C12: 45133 | D12: Sports | E12: Resistance Bands | F12: 19.99 | G12: 3 | H12: 0 | I12: 19.99 | J12: 59.97 | K12: UPI | L12: Delivered | M12: 5 | N12: =VLOOKUP(B12,Customers!A:J,7,0) -> 29 | O12: =VLOOKUP(B12,Customers!A:J,5,0) -> San Diego | P12: =VLOOKUP(B12,Customers!A:J,10,0) -> Free | Q12: =VLOOKUP(B12,Customers!A:J,8,0) -> Female | R12: =ISNUMBER(C12) -> TRUE | S12: =DATE(YEAR(C12),MONTH(C12),1) -> 45108
A13: ORD-20012 | B13: CUST-5003 | C13: 44931 | D13: Toys | E13: Puzzle 1000pcs | F13: 24.99 | G13: 1 | H13: 10 | I13: 22.49 | J13: 22.49 | K13: PayPal | L13: Cancelled | M13: 3 | N13: =VLOOKUP(B13,Customers!A:J,7,0) -> 29 | O13: =VLOOKUP(B13,Customers!A:J,5,0) -> San Diego | P13: =VLOOKUP(B13,Customers!A:J,10,0) -> Free | Q13: =VLOOKUP(B13,Customers!A:J,8,0) -> Female | R13: =ISNUMBER(C13) -> TRUE | S13: =DATE(YEAR(C13),MONTH(C13),1) -> 44927
A14: ORD-20013 | B14: CUST-5003 | C14: 44621 | D14: Home & Kitchen | E14: Coffee Maker | F14: 59.99 | G14: 4 | H14: 0 | I14: 59.99 | J14: 239.96 | K14: UPI | L14: Delivered | M14: 5 | N14: =VLOOKUP(B14,Customers!A:J,7,0) -> 29 | O14: =VLOOKUP(B14,Customers!A:J,5,0) -> San Diego | P14: =VLOOKUP(B14,Customers!A:J,10,0) -> Free | Q14: =VLOOKUP(B14,Customers!A:J,8,0) -> Female | R14: =ISNUMBER(C14) -> TRUE | S14: =DATE(YEAR(C14),MONTH(C14),1) -> 44621
A15: ORD-20014 | B15: CUST-5003 | C15: 44736 | D15: Home & Kitchen | E15: Air Fryer | F15: 89.99 | G15: 1 | H15: 5 | I15: 85.49 | J15: 85.49 | K15: Wallet | L15: Delivered | M15: 5 | N15: =VLOOKUP(B15,Customers!A:J,7,0) -> 29 | O15: =VLOOKUP(B15,Customers!A:J,5,0) -> San Diego | P15: =VLOOKUP(B15,Customers!A:J,10,0) -> Free | Q15: =VLOOKUP(B15,Customers!A:J,8,0) -> Female | R15: =ISNUMBER(C15) -> TRUE | S15: =DATE(YEAR(C15),MONTH(C15),1) -> 44713
A16: ORD-20015 | B16: CUST-5003 | C16: 44637 | D16: Electronics | E16: Smart Watch | F16: 199.99 | G16: 3 | H16: 10 | I16: 179.99 | J16: 539.97 | K16: Credit Card | L16: Delivered | N16: =VLOOKUP(B16,Customers!A:J,7,0) -> 29 | O16: =VLOOKUP(B16,Customers!A:J,5,0) -> San Diego | P16: =VLOOKUP(B16,Customers!A:J,10,0) -> Free | Q16: =VLOOKUP(B16,Customers!A:J,8,0) -> Female | R16: =ISNUMBER(C16) -> TRUE | S16: =DATE(YEAR(C16),MONTH(C16),1) -> 44621
A17: ORD-20016 | B17: CUST-5003 | C17: 44657 | D17: Electronics | E17: Wireless Earbuds | F17: 79.99 | G17: 1 | H17: 5 | I17: 75.99 | J17: 75.99 | K17: PayPal | L17: Delivered | M17: 5 | N17: =VLOOKUP(B17,Customers!A:J,7,0) -> 29 | O17: =VLOOKUP(B17,Customers!A:J,5,0) -> San Diego | P17: =VLOOKUP(B17,Customers!A:J,10,0) -> Free | Q17: =VLOOKUP(B17,Customers!A:J,8,0) -> Female | R17: =ISNUMBER(C17) -> TRUE | S17: =DATE(YEAR(C17),MONTH(C17),1) -> 44652
A18: ORD-20017 | B18: CUST-5003 | C18: 45210 | D18: Sports | E18: Water Bottle | F18: 24.99 | G18: 3 | H18: 20 | I18: 19.99 | J18: 59.97 | K18: Wallet | L18: Delivered | N18: =VLOOKUP(B18,Customers!A:J,7,0) -> 29 | O18: =VLOOKUP(B18,Customers!A:J,5,0) -> San Diego | P18: =VLOOKUP(B18,Customers!A:J,10,0) -> Free | Q18: =VLOOKUP(B18,Customers!A:J,8,0) -> Female | R18: =ISNUMBER(C18) -> TRUE | S18: =DATE(YEAR(C18),MONTH(C18),1) -> 45200
A19: ORD-20018 | B19: CUST-5003 | C19: 45262 | D19: Beauty | E19: Lip Balm Set | F19: 14.99 | G19: 3 | H19: 5 | I19: 14.24 | J19: 42.72 | K19: Credit Card | L19: Delivered | M19: 4 | N19: =VLOOKUP(B19,Customers!A:J,7,0) -> 29 | O19: =VLOOKUP(B19,Customers!A:J,5,0) -> San Diego | P19: =VLOOKUP(B19,Customers!A:J,10,0) -> Free | Q19: =VLOOKUP(B19,Customers!A:J,8,0) -> Female | R19: =ISNUMBER(C19) -> TRUE | S19: =DATE(YEAR(C19),MONTH(C19),1) -> 45261
A20: ORD-20019 | B20: CUST-5004 | C20: 45484 | D20: Home & Kitchen | E20: Non-stick Pan Set | F20: 44.99 | G20: 1 | H20: 20 | I20: 35.99 | J20: 35.99 | K20: PayPal | L20: Delivered | M20: 5 | N20: =VLOOKUP(B20,Customers!A:J,7,0) -> 32 | O20: =VLOOKUP(B20,Customers!A:J,5,0) -> Dallas | P20: =VLOOKUP(B20,Customers!A:J,10,0) -> Free | Q20: =VLOOKUP(B20,Customers!A:J,8,0) -> Male | R20: =ISNUMBER(C20) -> TRUE | S20: =DATE(YEAR(C20),MONTH(C20),1) -> 45474
A21: ORD-20020 | B21: CUST-5004 | C21: 44949 | D21: Home & Kitchen | E21: Coffee Maker | F21: 59.99 | G21: 2 | H21: 0 | I21: 59.99 | J21: 119.98 | K21: Debit Card | L21: Delivered | M21: 5 | N21: =VLOOKUP(B21,Customers!A:J,7,0) -> 32 | O21: =VLOOKUP(B21,Customers!A:J,5,0) -> Dallas | P21: =VLOOKUP(B21,Customers!A:J,10,0) -> Free | Q21: =VLOOKUP(B21,Customers!A:J,8,0) -> Male | R21: =ISNUMBER(C21) -> TRUE | S21: =DATE(YEAR(C21),MONTH(C21),1) -> 44927
A22: ORD-20021 | B22: CUST-5004 | C22: 44642 | D22: Home & Kitchen | E22: Non-stick Pan Set | F22: 44.99 | G22: 4 | H22: 15 | I22: 38.24 | J22: 152.96 | K22: Credit Card | L22: Delivered | M22: 5 | N22: =VLOOKUP(B22,Customers!A:J,7,0) -> 32 | O22: =VLOOKUP(B22,Customers!A:J,5,0) -> Dallas | P22: =VLOOKUP(B22,Customers!A:J,10,0) -> Free | Q22: =VLOOKUP(B22,Customers!A:J,8,0) -> Male | R22: =ISNUMBER(C22) -> TRUE | S22: =DATE(YEAR(C22),MONTH(C22),1) -> 44621
A23: ORD-20022 | B23: CUST-5004 | C23: 45554 | D23: Beauty | E23: Hair Mask | F23: 24.99 | G23: 4 | H23: 0 | I23: 24.99 | J23: 99.96 | K23: Credit Card | L23: Delivered | M23: 1 | N23: =VLOOKUP(B23,Customers!A:J,7,0) -> 32 | O23: =VLOOKUP(B23,Customers!A:J,5,0) -> Dallas | P23: =VLOOKUP(B23,Customers!A:J,10,0) -> Free | Q23: =VLOOKUP(B23,Customers!A:J,8,0) -> Male | R23: =ISNUMBER(C23) -> TRUE | S23: =DATE(YEAR(C23),MONTH(C23),1) -> 45536
A24: ORD-20023 | B24: CUST-5004 | C24: 45367 | D24: Clothing | E24: Running Shoes | F24: 89.99 | G24: 2 | H24: 10 | I24: 80.99 | J24: 161.98 | K24: UPI | L24: Delivered | M24: 4 | N24: =VLOOKUP(B24,Customers!A:J,7,0) -> 32 | O24: =VLOOKUP(B24,Customers!A:J,5,0) -> Dallas | P24: =VLOOKUP(B24,Customers!A:J,10,0) -> Free | Q24: =VLOOKUP(B24,Customers!A:J,8,0) -> Male | R24: =ISNUMBER(C24) -> TRUE | S24: =DATE(YEAR(C24),MONTH(C24),1) -> 45352
A25: ORD-20024 | B25: CUST-5004 | C25: 45603 | D25: Books | E25: Fiction Novel | F25: 14.99 | G25: 1 | H25: 10 | I25: 13.49 | J25: 13.49 | K25: Credit Card | L25: Delivered | M25: 5 | N25: =VLOOKUP(B25,Customers!A:J,7,0) -> 32 | O25: =VLOOKUP(B25,Customers!A:J,5,0) -> Dallas | P25: =VLOOKUP(B25,Customers!A:J,10,0) -> Free | Q25: =VLOOKUP(B25,Customers!A:J,8,0) -> Male | R25: =ISNUMBER(C25) -> TRUE | S25: =DATE(YEAR(C25),MONTH(C25),1) -> 45597
A26: ORD-20025 | B26: CUST-5004 | C26: 44946 | D26: Beauty | E26: Face Serum | F26: 39.99 | G26: 4 | H26: 10 | I26: 35.99 | J26: 143.96 | K26: Wallet | L26: Delivered | N26: =VLOOKUP(B26,Customers!A:J,7,0) -> 32 | O26: =VLOOKUP(B26,Customers!A:J,5,0) -> Dallas | P26: =VLOOKUP(B26,Customers!A:J,10,0) -> Free | Q26: =VLOOKUP(B26,Customers!A:J,8,0) -> Male | R26: =ISNUMBER(C26) -> TRUE | S26: =DATE(YEAR(C26),MONTH(C26),1) -> 44927
A27: ORD-20026 | B27: CUST-5004 | C27: 45364 | D27: Beauty | E27: Hair Mask | F27: 24.99 | G27: 2 | H27: 15 | I27: 21.24 | J27: 42.48 | K27: Wallet | L27: Delivered | M27: 4 | N27: =VLOOKUP(B27,Customers!A:J,7,0) -> 32 | O27: =VLOOKUP(B27,Customers!A:J,5,0) -> Dallas | P27: =VLOOKUP(B27,Customers!A:J,10,0) -> Free | Q27: =VLOOKUP(B27,Customers!A:J,8,0) -> Male | R27: =ISNUMBER(C27) -> TRUE | S27: =DATE(YEAR(C27),MONTH(C27),1) -> 45352
A28: ORD-20027 | B28: CUST-5004 | C28: 44619 | D28: Clothing | E28: Yoga Pants | F28: 44.99 | G28: 2 | H28: 5 | I28: 42.74 | J28: 85.48 | K28: UPI | L28: Delivered | M28: 3 | N28: =VLOOKUP(B28,Customers!A:J,7,0) -> 32 | O28: =VLOOKUP(B28,Customers!A:J,5,0) -> Dallas | P28: =VLOOKUP(B28,Customers!A:J,10,0) -> Free | Q28: =VLOOKUP(B28,Customers!A:J,8,0) -> Male | R28: =ISNUMBER(C28) -> TRUE | S28: =DATE(YEAR(C28),MONTH(C28),1) -> 44593
A29: ORD-20028 | B29: CUST-5004 | C29: 44621 | D29: Clothing | E29: Yoga Pants | F29: 44.99 | G29: 1 | H29: 0 | I29: 44.99 | J29: 44.99 | K29: Debit Card | L29: Delivered | M29: 5 | N29: =VLOOKUP(B29,Customers!A:J,7,0) -> 32 | O29: =VLOOKUP(B29,Customers!A:J,5,0) -> Dallas | P29: =VLOOKUP(B29,Customers!A:J,10,0) -> Free | Q29: =VLOOKUP(B29,Customers!A:J,8,0) -> Male | R29: =ISNUMBER(C29) -> TRUE | S29: =DATE(YEAR(C29),MONTH(C29),1) -> 44621
A30: ORD-20029 | B30: CUST-5004 | C30: 45028 | D30: Beauty | E30: Face Serum | F30: 39.99 | G30: 3 | H30: 20 | I30: 31.99 | J30: 95.97 | K30: Credit Card | L30: Processing | N30: =VLOOKUP(B30,Customers!A:J,7,0) -> 32 | O30: =VLOOKUP(B30,Customers!A:J,5,0) -> Dallas | P30: =VLOOKUP(B30,Customers!A:J,10,0) -> Free | Q30: =VLOOKUP(B30,Customers!A:J,8,0) -> Male | R30: =ISNUMBER(C30) -> TRUE | S30: =DATE(YEAR(C30),MONTH(C30),1) -> 45017
A31: ORD-20030 | B31: CUST-5004 | C31: 45093 | D31: Electronics | E31: Smart Watch | F31: 199.99 | G31: 4 | H31: 20 | I31: 159.99 | J31: 639.96 | K31: UPI | L31: Delivered | M31: 5 | N31: =VLOOKUP(B31,Customers!A:J,7,0) -> 32 | O31: =VLOOKUP(B31,Customers!A:J,5,0) -> Dallas | P31: =VLOOKUP(B31,Customers!A:J,10,0) -> Free | Q31: =VLOOKUP(B31,Customers!A:J,8,0) -> Male | R31: =ISNUMBER(C31) -> TRUE | S31: =DATE(YEAR(C31),MONTH(C31),1) -> 45078
A32: ORD-20031 | B32: CUST-5004 | C32: 44840 | D32: Toys | E32: Action Figure | F32: 19.99 | G32: 4 | H32: 0 | I32: 19.99 | J32: 79.96 | K32: Debit Card | L32: Delivered | M32: 5 | N32: =VLOOKUP(B32,Customers!A:J,7,0) -> 32 | O32: =VLOOKUP(B32,Customers!A:J,5,0) -> Dallas | P32: =VLOOKUP(B32,Customers!A:J,10,0) -> Free | Q32: =VLOOKUP(B32,Customers!A:J,8,0) -> Male | R32: =ISNUMBER(C32) -> TRUE | S32: =DATE(YEAR(C32),MONTH(C32),1) -> 44835
A33: ORD-20032 | B33: CUST-5005 | C33: 45209 | D33: Beauty | E33: Moisturizer SPF 50 | F33: 29.99 | G33: 3 | H33: 20 | I33: 23.99 | J33: 71.97 | K33: Wallet | L33: Delivered | N33: =VLOOKUP(B33,Customers!A:J,7,0) -> 24 | O33: =VLOOKUP(B33,Customers!A:J,5,0) -> Houston | P33: =VLOOKUP(B33,Customers!A:J,10,0) -> Free | Q33: =VLOOKUP(B33,Customers!A:J,8,0) -> Male | R33: =ISNUMBER(C33) -> TRUE | S33: =DATE(YEAR(C33),MONTH(C33),1) -> 45200
A34: ORD-20033 | B34: CUST-5005 | C34: 45575 | D34: Clothing | E34: Running Shoes | F34: 89.99 | G34: 1 | H34: 0 | I34: 89.99 | J34: 89.99 | K34: UPI | L34: Delivered | M34: 5 | N34: =VLOOKUP(B34,Customers!A:J,7,0) -> 24 | O34: =VLOOKUP(B34,Customers!A:J,5,0) -> Houston | P34: =VLOOKUP(B34,Customers!A:J,10,0) -> Free | Q34: =VLOOKUP(B34,Customers!A:J,8,0) -> Male | R34: =ISNUMBER(C34) -> TRUE | S34: =DATE(YEAR(C34),MONTH(C34),1) -> 45566
A35: ORD-20034 | B35: CUST-5005 | C35: 44815 | D35: Sports | E35: Jump Rope | F35: 14.99 | G35: 2 | H35: 0 | I35: 14.99 | J35: 29.98 | K35: Credit Card | L35: Delivered | M35: 3 | N35: =VLOOKUP(B35,Customers!A:J,7,0) -> 24 | O35: =VLOOKUP(B35,Customers!A:J,5,0) -> Houston | P35: =VLOOKUP(B35,Customers!A:J,10,0) -> Free | Q35: =VLOOKUP(B35,Customers!A:J,8,0) -> Male | R35: =ISNUMBER(C35) -> TRUE | S35: =DATE(YEAR(C35),MONTH(C35),1) -> 44805
A36: ORD-20035 | B36: CUST-5005 | C36: 44878 | D36: Books | E36: Fiction Novel | F36: 14.99 | G36: 1 | H36: 15 | I36: 12.74 | J36: 12.74 | K36: UPI | L36: Delivered | M36: 5 | N36: =VLOOKUP(B36,Customers!A:J,7,0) -> 24 | O36: =VLOOKUP(B36,Customers!A:J,5,0) -> Houston | P36: =VLOOKUP(B36,Customers!A:J,10,0) -> Free | Q36: =VLOOKUP(B36,Customers!A:J,8,0) -> Male | R36: =ISNUMBER(C36) -> TRUE | S36: =DATE(YEAR(C36),MONTH(C36),1) -> 44866
A37: ORD-20036 | B37: CUST-5005 | C37: 45220 | D37: Beauty | E37: Moisturizer SPF 50 | F37: 29.99 | G37: 1 | H37: 20 | I37: 23.99 | J37: 23.99 | K37: PayPal | L37: Delivered | M37: 3 | N37: =VLOOKUP(B37,Customers!A:J,7,0) -> 24 | O37: =VLOOKUP(B37,Customers!A:J,5,0) -> Houston | P37: =VLOOKUP(B37,Customers!A:J,10,0) -> Free | Q37: =VLOOKUP(B37,Customers!A:J,8,0) -> Male | R37: =ISNUMBER(C37) -> TRUE | S37: =DATE(YEAR(C37),MONTH(C37),1) -> 45200
A38: ORD-20037 | B38: CUST-5005 | C38: 45579 | D38: Home & Kitchen | E38: Air Fryer | F38: 89.99 | G38: 2 | H38: 20 | I38: 71.99 | J38: 143.98 | K38: Debit Card | L38: Delivered | M38: 5 | N38: =VLOOKUP(B38,Customers!A:J,7,0) -> 24 | O38: =VLOOKUP(B38,Customers!A:J,5,0) -> Houston | P38: =VLOOKUP(B38,Customers!A:J,10,0) -> Free | Q38: =VLOOKUP(B38,Customers!A:J,8,0) -> Male | R38: =ISNUMBER(C38) -> TRUE | S38: =DATE(YEAR(C38),MONTH(C38),1) -> 45566
A39: ORD-20038 | B39: CUST-5005 | C39: 44939 | D39: Electronics | E39: Bluetooth Speaker | F39: 49.99 | G39: 1 | H39: 15 | I39: 42.49 | J39: 42.49 | K39: Wallet | L39: Delivered | N39: =VLOOKUP(B39,Customers!A:J,7,0) -> 24 | O39: =VLOOKUP(B39,Customers!A:J,5,0) -> Houston | P39: =VLOOKUP(B39,Customers!A:J,10,0) -> Free | Q39: =VLOOKUP(B39,Customers!A:J,8,0) -> Male | R39: =ISNUMBER(C39) -> TRUE | S39: =DATE(YEAR(C39),MONTH(C39),1) -> 44927
A40: ORD-20039 | B40: CUST-5005 | C40: 45009 | D40: Electronics | E40: Wireless Earbuds | F40: 79.99 | G40: 3 | H40: 5 | I40: 75.99 | J40: 227.97 | K40: Wallet | L40: Delivered | M40: 5 | N40: =VLOOKUP(B40,Customers!A:J,7,0) -> 24 | O40: =VLOOKUP(B40,Customers!A:J,5,0) -> Houston | P40: =VLOOKUP(B40,Customers!A:J,10,0) -> Free | Q40: =VLOOKUP(B40,Customers!A:J,8,0) -> Male | R40: =ISNUMBER(C40) -> TRUE | S40: =DATE(YEAR(C40),MONTH(C40),1) -> 44986
A41: ORD-20040 | B41: CUST-5005 | C41: 45156 | D41: Toys | E41: LEGO Classic Set | F41: 49.99 | G41: 3 | H41: 20 | I41: 39.99 | J41: 119.97 | K41: UPI | L41: Delivered | N41: =VLOOKUP(B41,Customers!A:J,7,0) -> 24 | O41: =VLOOKUP(B41,Customers!A:J,5,0) -> Houston | P41: =VLOOKUP(B41,Customers!A:J,10,0) -> Free | Q41: =VLOOKUP(B41,Customers!A:J,8,0) -> Male | R41: =ISNUMBER(C41) -> TRUE | S41: =DATE(YEAR(C41),MONTH(C41),1) -> 45139
A42: ORD-20041 | B42: CUST-5006 | C42: 44638 | D42: Sports | E42: Resistance Bands | F42: 19.99 | G42: 1 | H42: 15 | I42: 16.99 | J42: 16.99 | K42: Debit Card | L42: Delivered | M42: 4 | N42: =VLOOKUP(B42,Customers!A:J,7,0) -> 52 | O42: =VLOOKUP(B42,Customers!A:J,5,0) -> Los Angeles | P42: =VLOOKUP(B42,Customers!A:J,10,0) -> Free | Q42: =VLOOKUP(B42,Customers!A:J,8,0) -> Male | R42: =ISNUMBER(C42) -> TRUE | S42: =DATE(YEAR(C42),MONTH(C42),1) -> 44621
A43: ORD-20042 | B43: CUST-5006 | C43: 45483 | D43: Clothing | E43: Cotton T-Shirt | F43: 24.99 | G43: 4 | H43: 0 | I43: 24.99 | J43: 99.96 | K43: Credit Card | L43: Delivered | N43: =VLOOKUP(B43,Customers!A:J,7,0) -> 52 | O43: =VLOOKUP(B43,Customers!A:J,5,0) -> Los Angeles | P43: =VLOOKUP(B43,Customers!A:J,10,0) -> Free | Q43: =VLOOKUP(B43,Customers!A:J,8,0) -> Male | R43: =ISNUMBER(C43) -> TRUE | S43: =DATE(YEAR(C43),MONTH(C43),1) -> 45474
A44: ORD-20043 | B44: CUST-5006 | C44: 45294 | D44: Books | E44: Data Science Handbook | F44: 49.99 | G44: 1 | H44: 0 | I44: 49.99 | J44: 49.99 | K44: Wallet | L44: Delivered | M44: 4 | N44: =VLOOKUP(B44,Customers!A:J,7,0) -> 52 | O44: =VLOOKUP(B44,Customers!A:J,5,0) -> Los Angeles | P44: =VLOOKUP(B44,Customers!A:J,10,0) -> Free | Q44: =VLOOKUP(B44,Customers!A:J,8,0) -> Male | R44: =ISNUMBER(C44) -> TRUE | S44: =DATE(YEAR(C44),MONTH(C44),1) -> 45292
A45: ORD-20044 | B45: CUST-5006 | C45: 44800 | D45: Books | E45: Business Analytics | F45: 39.99 | G45: 4 | H45: 15 | I45: 33.99 | J45: 135.96 | K45: Debit Card | L45: Delivered | M45: 5 | N45: =VLOOKUP(B45,Customers!A:J,7,0) -> 52 | O45: =VLOOKUP(B45,Customers!A:J,5,0) -> Los Angeles | P45: =VLOOKUP(B45,Customers!A:J,10,0) -> Free | Q45: =VLOOKUP(B45,Customers!A:J,8,0) -> Male | R45: =ISNUMBER(C45) -> TRUE | S45: =DATE(YEAR(C45),MONTH(C45),1) -> 44774
A46: ORD-20045 | B46: CUST-5006 | C46: 44735 | D46: Sports | E46: Jump Rope | F46: 14.99 | G46: 2 | H46: 15 | I46: 12.74 | J46: 25.48 | K46: Credit Card | L46: Delivered | M46: 5 | N46: =VLOOKUP(B46,Customers!A:J,7,0) -> 52 | O46: =VLOOKUP(B46,Customers!A:J,5,0) -> Los Angeles | P46: =VLOOKUP(B46,Customers!A:J,10,0) -> Free | Q46: =VLOOKUP(B46,Customers!A:J,8,0) -> Male | R46: =ISNUMBER(C46) -> TRUE | S46: =DATE(YEAR(C46),MONTH(C46),1) -> 44713
A47: ORD-20046 | B47: CUST-5006 | C47: 45530 | D47: Home & Kitchen | E47: Air Fryer | F47: 89.99 | G47: 1 | H47: 15 | I47: 76.49 | J47: 76.49 | K47: Debit Card | L47: Processing | M47: 5 | N47: =VLOOKUP(B47,Customers!A:J,7,0) -> 52 | O47: =VLOOKUP(B47,Customers!A:J,5,0) -> Los Angeles | P47: =VLOOKUP(B47,Customers!A:J,10,0) -> Free | Q47: =VLOOKUP(B47,Customers!A:J,8,0) -> Male | R47: =ISNUMBER(C47) -> TRUE | S47: =DATE(YEAR(C47),MONTH(C47),1) -> 45505
A48: ORD-20047 | B48: CUST-5006 | C48: 44792 | D48: Toys | E48: Action Figure | F48: 19.99 | G48: 4 | H48: 0 | I48: 19.99 | J48: 79.96 | K48: Debit Card | L48: Delivered | M48: 5 | N48: =VLOOKUP(B48,Customers!A:J,7,0) -> 52 | O48: =VLOOKUP(B48,Customers!A:J,5,0) -> Los Angeles | P48: =VLOOKUP(B48,Customers!A:J,10,0) -> Free | Q48: =VLOOKUP(B48,Customers!A:J,8,0) -> Male | R48: =ISNUMBER(C48) -> TRUE | S48: =DATE(YEAR(C48),MONTH(C48),1) -> 44774
A49: ORD-20048 | B49: CUST-5006 | C49: 45003 | D49: Home & Kitchen | E49: Coffee Maker | F49: 59.99 | G49: 4 | H49: 0 | I49: 59.99 | J49: 239.96 | K49: UPI | L49: Delivered | M49: 3 | N49: =VLOOKUP(B49,Customers!A:J,7,0) -> 52 | O49: =VLOOKUP(B49,Customers!A:J,5,0) -> Los Angeles | P49: =VLOOKUP(B49,Customers!A:J,10,0) -> Free | Q49: =VLOOKUP(B49,Customers!A:J,8,0) -> Male | R49: =ISNUMBER(C49) -> TRUE | S49: =DATE(YEAR(C49),MONTH(C49),1) -> 44986
A50: ORD-20049 | B50: CUST-5006 | C50: 44723 | D50: Sports | E50: Yoga Mat | F50: 29.99 | G50: 4 | H50: 0 | I50: 29.99 | J50: 119.96 | K50: PayPal | L50: Delivered | M50: 3 | N50: =VLOOKUP(B50,Customers!A:J,7,0) -> 52 | O50: =VLOOKUP(B50,Customers!A:J,5,0) -> Los Angeles | P50: =VLOOKUP(B50,Customers!A:J,10,0) -> Free | Q50: =VLOOKUP(B50,Customers!A:J,8,0) -> Male | R50: =ISNUMBER(C50) -> TRUE | S50: =DATE(YEAR(C50),MONTH(C50),1) -> 44713
A51: ORD-20050 | B51: CUST-5006 | C51: 44619 | D51: Home & Kitchen | E51: Non-stick Pan Set | F51: 44.99 | G51: 2 | H51: 0 | I51: 44.99 | J51: 89.98 | K51: Debit Card | L51: Delivered | N51: =VLOOKUP(B51,Customers!A:J,7,0) -> 52 | O51: =VLOOKUP(B51,Customers!A:J,5,0) -> Los Angeles | P51: =VLOOKUP(B51,Customers!A:J,10,0) -> Free | Q51: =VLOOKUP(B51,Customers!A:J,8,0) -> Male | R51: =ISNUMBER(C51) -> TRUE | S51: =DATE(YEAR(C51),MONTH(C51),1) -> 44593
A52: ORD-20051 | B52: CUST-5006 | C52: 45070 | D52: Home & Kitchen | E52: Air Fryer | F52: 89.99 | G52: 1 | H52: 0 | I52: 89.99 | J52: 89.99 | K52: Credit Card | L52: Returned | N52: =VLOOKUP(B52,Customers!A:J,7,0) -> 52 | O52: =VLOOKUP(B52,Customers!A:J,5,0) -> Los Angeles | P52: =VLOOKUP(B52,Customers!A:J,10,0) -> Free | Q52: =VLOOKUP(B52,Customers!A:J,8,0) -> Male | R52: =ISNUMBER(C52) -> TRUE | S52: =DATE(YEAR(C52),MONTH(C52),1) -> 45047
A53: ORD-20052 | B53: CUST-5006 | C53: 45131 | D53: Sports | E53: Jump Rope | F53: 14.99 | G53: 2 | H53: 5 | I53: 14.24 | J53: 28.48 | K53: Wallet | L53: Shipped | M53: 5 | N53: =VLOOKUP(B53,Customers!A:J,7,0) -> 52 | O53: =VLOOKUP(B53,Customers!A:J,5,0) -> Los Angeles | P53: =VLOOKUP(B53,Customers!A:J,10,0) -> Free | Q53: =VLOOKUP(B53,Customers!A:J,8,0) -> Male | R53: =ISNUMBER(C53) -> TRUE | S53: =DATE(YEAR(C53),MONTH(C53),1) -> 45108
A54: ORD-20053 | B54: CUST-5006 | C54: 45389 | D54: Beauty | E54: Moisturizer SPF 50 | F54: 29.99 | G54: 2 | H54: 10 | I54: 26.99 | J54: 53.98 | K54: PayPal | L54: Delivered | N54: =VLOOKUP(B54,Customers!A:J,7,0) -> 52 | O54: =VLOOKUP(B54,Customers!A:J,5,0) -> Los Angeles | P54: =VLOOKUP(B54,Customers!A:J,10,0) -> Free | Q54: =VLOOKUP(B54,Customers!A:J,8,0) -> Male | R54: =ISNUMBER(C54) -> TRUE | S54: =DATE(YEAR(C54),MONTH(C54),1) -> 45383
A55: ORD-20054 | B55: CUST-5007 | C55: 44639 | D55: Sports | E55: Water Bottle | F55: 24.99 | G55: 2 | H55: 0 | I55: 24.99 | J55: 49.98 | K55: Wallet | L55: Delivered | N55: =VLOOKUP(B55,Customers!A:J,7,0) -> 43 | O55: =VLOOKUP(B55,Customers!A:J,5,0) -> Dallas | P55: =VLOOKUP(B55,Customers!A:J,10,0) -> Silver | Q55: =VLOOKUP(B55,Customers!A:J,8,0) -> Male | R55: =ISNUMBER(C55) -> TRUE | S55: =DATE(YEAR(C55),MONTH(C55),1) -> 44621
A56: ORD-20055 | B56: CUST-5007 | C56: 45387 | D56: Sports | E56: Resistance Bands | F56: 19.99 | G56: 2 | H56: 0 | I56: 19.99 | J56: 39.98 | K56: Debit Card | L56: Delivered | M56: 5 | N56: =VLOOKUP(B56,Customers!A:J,7,0) -> 43 | O56: =VLOOKUP(B56,Customers!A:J,5,0) -> Dallas | P56: =VLOOKUP(B56,Customers!A:J,10,0) -> Silver | Q56: =VLOOKUP(B56,Customers!A:J,8,0) -> Male | R56: =ISNUMBER(C56) -> TRUE | S56: =DATE(YEAR(C56),MONTH(C56),1) -> 45383
A57: ORD-20056 | B57: CUST-5007 | C57: 45272 | D57: Sports | E57: Water Bottle | F57: 24.99 | G57: 3 | H57: 20 | I57: 19.99 | J57: 59.97 | K57: UPI | L57: Delivered | N57: =VLOOKUP(B57,Customers!A:J,7,0) -> 43 | O57: =VLOOKUP(B57,Customers!A:J,5,0) -> Dallas | P57: =VLOOKUP(B57,Customers!A:J,10,0) -> Silver | Q57: =VLOOKUP(B57,Customers!A:J,8,0) -> Male | R57: =ISNUMBER(C57) -> TRUE | S57: =DATE(YEAR(C57),MONTH(C57),1) -> 45261
A58: ORD-20057 | B58: CUST-5007 | C58: 44903 | D58: Clothing | E58: Yoga Pants | F58: 44.99 | G58: 4 | H58: 20 | I58: 35.99 | J58: 143.96 | K58: UPI | L58: Delivered | N58: =VLOOKUP(B58,Customers!A:J,7,0) -> 43 | O58: =VLOOKUP(B58,Customers!A:J,5,0) -> Dallas | P58: =VLOOKUP(B58,Customers!A:J,10,0) -> Silver | Q58: =VLOOKUP(B58,Customers!A:J,8,0) -> Male | R58: =ISNUMBER(C58) -> TRUE | S58: =DATE(YEAR(C58),MONTH(C58),1) -> 44896
A59: ORD-20058 | B59: CUST-5007 | C59: 45100 | D59: Home & Kitchen | E59: Air Fryer | F59: 89.99 | G59: 4 | H59: 0 | I59: 89.99 | J59: 359.96 | K59: Debit Card | L59: Shipped | M59: 5 | N59: =VLOOKUP(B59,Customers!A:J,7,0) -> 43 | O59: =VLOOKUP(B59,Customers!A:J,5,0) -> Dallas | P59: =VLOOKUP(B59,Customers!A:J,10,0) -> Silver | Q59: =VLOOKUP(B59,Customers!A:J,8,0) -> Male | R59: =ISNUMBER(C59) -> TRUE | S59: =DATE(YEAR(C59),MONTH(C59),1) -> 45078
A60: ORD-20059 | B60: CUST-5007 | C60: 44607 | D60: Clothing | E60: Denim Jacket | F60: 69.99 | G60: 2 | H60: 20 | I60: 55.99 | J60: 111.98 | K60: Credit Card | L60: Delivered | N60: =VLOOKUP(B60,Customers!A:J,7,0) -> 43 | O60: =VLOOKUP(B60,Customers!A:J,5,0) -> Dallas | P60: =VLOOKUP(B60,Customers!A:J,10,0) -> Silver | Q60: =VLOOKUP(B60,Customers!A:J,8,0) -> Male | R60: =ISNUMBER(C60) -> TRUE | S60: =DATE(YEAR(C60),MONTH(C60),1) -> 44593
A61: ORD-20060 | B61: CUST-5007 | C61: 44670 | D61: Books | E61: Fiction Novel | F61: 14.99 | G61: 1 | H61: 10 | I61: 13.49 | J61: 13.49 | K61: Wallet | L61: Delivered | M61: 5 | N61: =VLOOKUP(B61,Customers!A:J,7,0) -> 43 | O61: =VLOOKUP(B61,Customers!A:J,5,0) -> Dallas | P61: =VLOOKUP(B61,Customers!A:J,10,0) -> Silver | Q61: =VLOOKUP(B61,Customers!A:J,8,0) -> Male | R61: =ISNUMBER(C61) -> TRUE | S61: =DATE(YEAR(C61),MONTH(C61),1) -> 44652
A62: ORD-20061 | B62: CUST-5007 | C62: 45606 | D62: Beauty | E62: Hair Mask | F62: 24.99 | G62: 4 | H62: 15 | I62: 21.24 | J62: 84.96 | K62: Credit Card | L62: Delivered | N62: =VLOOKUP(B62,Customers!A:J,7,0) -> 43 | O62: =VLOOKUP(B62,Customers!A:J,5,0) -> Dallas | P62: =VLOOKUP(B62,Customers!A:J,10,0) -> Silver | Q62: =VLOOKUP(B62,Customers!A:J,8,0) -> Male | R62: =ISNUMBER(C62) -> TRUE | S62: =DATE(YEAR(C62),MONTH(C62),1) -> 45597
A63: ORD-20062 | B63: CUST-5007 | C63: 45118 | D63: Sports | E63: Jump Rope | F63: 14.99 | G63: 2 | H63: 20 | I63: 11.99 | J63: 23.98 | K63: Debit Card | L63: Delivered | M63: 4 | N63: =VLOOKUP(B63,Customers!A:J,7,0) -> 43 | O63: =VLOOKUP(B63,Customers!A:J,5,0) -> Dallas | P63: =VLOOKUP(B63,Customers!A:J,10,0) -> Silver | Q63: =VLOOKUP(B63,Customers!A:J,8,0) -> Male | R63: =ISNUMBER(C63) -> TRUE | S63: =DATE(YEAR(C63),MONTH(C63),1) -> 45108
A64: ORD-20063 | B64: CUST-5007 | C64: 44610 | D64: Beauty | E64: Moisturizer SPF 50 | F64: 29.99 | G64: 2 | H64: 0 | I64: 29.99 | J64: 59.98 | K64: Debit Card | L64: Delivered | M64: 5 | N64: =VLOOKUP(B64,Customers!A:J,7,0) -> 43 | O64: =VLOOKUP(B64,Customers!A:J,5,0) -> Dallas | P64: =VLOOKUP(B64,Customers!A:J,10,0) -> Silver | Q64: =VLOOKUP(B64,Customers!A:J,8,0) -> Male | R64: =ISNUMBER(C64) -> TRUE | S64: =DATE(YEAR(C64),MONTH(C64),1) -> 44593
A65: ORD-20064 | B65: CUST-5007 | C65: 45394 | D65: Toys | E65: Action Figure | F65: 19.99 | G65: 2 | H65: 10 | I65: 17.99 | J65: 35.98 | K65: Credit Card | L65: Delivered | M65: 3 | N65: =VLOOKUP(B65,Customers!A:J,7,0) -> 43 | O65: =VLOOKUP(B65,Customers!A:J,5,0) -> Dallas | P65: =VLOOKUP(B65,Customers!A:J,10,0) -> Silver | Q65: =VLOOKUP(B65,Customers!A:J,8,0) -> Male | R65: =ISNUMBER(C65) -> TRUE | S65: =DATE(YEAR(C65),MONTH(C65),1) -> 45383
A66: ORD-20065 | B66: CUST-5008 | C66: 44861 | D66: Electronics | E66: USB-C Hub | F66: 34.99 | G66: 3 | H66: 15 | I66: 29.74 | J66: 89.22 | K66: Credit Card | L66: Delivered | N66: =VLOOKUP(B66,Customers!A:J,7,0) -> 21 | O66: =VLOOKUP(B66,Customers!A:J,5,0) -> San Antonio | P66: =VLOOKUP(B66,Customers!A:J,10,0) -> Free | Q66: =VLOOKUP(B66,Customers!A:J,8,0) -> Female | R66: =ISNUMBER(C66) -> TRUE | S66: =DATE(YEAR(C66),MONTH(C66),1) -> 44835
A67: ORD-20066 | B67: CUST-5008 | C67: 45144 | D67: Electronics | E67: Smart Watch | F67: 199.99 | G67: 4 | H67: 0 | I67: 199.99 | J67: 799.96 | K67: Wallet | L67: Delivered | M67: 5 | N67: =VLOOKUP(B67,Customers!A:J,7,0) -> 21 | O67: =VLOOKUP(B67,Customers!A:J,5,0) -> San Antonio | P67: =VLOOKUP(B67,Customers!A:J,10,0) -> Free | Q67: =VLOOKUP(B67,Customers!A:J,8,0) -> Female | R67: =ISNUMBER(C67) -> TRUE | S67: =DATE(YEAR(C67),MONTH(C67),1) -> 45139
A68: ORD-20067 | B68: CUST-5008 | C68: 44629 | D68: Toys | E68: Remote Control Car | F68: 39.99 | G68: 4 | H68: 5 | I68: 37.99 | J68: 151.96 | K68: PayPal | L68: Delivered | M68: 5 | N68: =VLOOKUP(B68,Customers!A:J,7,0) -> 21 | O68: =VLOOKUP(B68,Customers!A:J,5,0) -> San Antonio | P68: =VLOOKUP(B68,Customers!A:J,10,0) -> Free | Q68: =VLOOKUP(B68,Customers!A:J,8,0) -> Female | R68: =ISNUMBER(C68) -> TRUE | S68: =DATE(YEAR(C68),MONTH(C68),1) -> 44621
A69: ORD-20068 | B69: CUST-5008 | C69: 45140 | D69: Home & Kitchen | E69: Blender | F69: 64.99 | G69: 3 | H69: 0 | I69: 64.99 | J69: 194.97 | K69: PayPal | L69: Delivered | M69: 5 | N69: =VLOOKUP(B69,Customers!A:J,7,0) -> 21 | O69: =VLOOKUP(B69,Customers!A:J,5,0) -> San Antonio | P69: =VLOOKUP(B69,Customers!A:J,10,0) -> Free | Q69: =VLOOKUP(B69,Customers!A:J,8,0) -> Female | R69: =ISNUMBER(C69) -> TRUE | S69: =DATE(YEAR(C69),MONTH(C69),1) -> 45139
A70: ORD-20069 | B70: CUST-5008 | C70: 45236 | D70: Toys | E70: Remote Control Car | F70: 39.99 | G70: 4 | H70: 0 | I70: 39.99 | J70: 159.96 | K70: Debit Card | L70: Delivered | M70: 4 | N70: =VLOOKUP(B70,Customers!A:J,7,0) -> 21 | O70: =VLOOKUP(B70,Customers!A:J,5,0) -> San Antonio | P70: =VLOOKUP(B70,Customers!A:J,10,0) -> Free | Q70: =VLOOKUP(B70,Customers!A:J,8,0) -> Female | R70: =ISNUMBER(C70) -> TRUE | S70: =DATE(YEAR(C70),MONTH(C70),1) -> 45231
A71: ORD-20070 | B71: CUST-5008 | C71: 45413 | D71: Books | E71: Business Analytics | F71: 39.99 | G71: 3 | H71: 5 | I71: 37.99 | J71: 113.97 | K71: Credit Card | L71: Delivered | N71: =VLOOKUP(B71,Customers!A:J,7,0) -> 21 | O71: =VLOOKUP(B71,Customers!A:J,5,0) -> San Antonio | P71: =VLOOKUP(B71,Customers!A:J,10,0) -> Free | Q71: =VLOOKUP(B71,Customers!A:J,8,0) -> Female | R71: =ISNUMBER(C71) -> TRUE | S71: =DATE(YEAR(C71),MONTH(C71),1) -> 45413
A72: ORD-20071 | B72: CUST-5008 | C72: 44901 | D72: Books | E72: Python for Beginners | F72: 29.99 | G72: 3 | H72: 0 | I72: 29.99 | J72: 89.97 | K72: UPI | L72: Delivered | M72: 5 | N72: =VLOOKUP(B72,Customers!A:J,7,0) -> 21 | O72: =VLOOKUP(B72,Customers!A:J,5,0) -> San Antonio | P72: =VLOOKUP(B72,Customers!A:J,10,0) -> Free | Q72: =VLOOKUP(B72,Customers!A:J,8,0) -> Female | R72: =ISNUMBER(C72) -> TRUE | S72: =DATE(YEAR(C72),MONTH(C72),1) -> 44896
A73: ORD-20072 | B73: CUST-5008 | C73: 44878 | D73: Books | E73: Python for Beginners | F73: 29.99 | G73: 3 | H73: 0 | I73: 29.99 | J73: 89.97 | K73: UPI | L73: Delivered | N73: =VLOOKUP(B73,Customers!A:J,7,0) -> 21 | O73: =VLOOKUP(B73,Customers!A:J,5,0) -> San Antonio | P73: =VLOOKUP(B73,Customers!A:J,10,0) -> Free | Q73: =VLOOKUP(B73,Customers!A:J,8,0) -> Female | R73: =ISNUMBER(C73) -> TRUE | S73: =DATE(YEAR(C73),MONTH(C73),1) -> 44866
A74: ORD-20073 | B74: CUST-5009 | C74: 44706 | D74: Toys | E74: Puzzle 1000pcs | F74: 24.99 | G74: 1 | H74: 15 | I74: 21.24 | J74: 21.24 | K74: Debit Card | L74: Delivered | M74: 4 | N74: =VLOOKUP(B74,Customers!A:J,7,0) -> 54 | O74: =VLOOKUP(B74,Customers!A:J,5,0) -> Philadelphia | P74: =VLOOKUP(B74,Customers!A:J,10,0) -> Silver | Q74: =VLOOKUP(B74,Customers!A:J,8,0) -> Female | R74: =ISNUMBER(C74) -> TRUE | S74: =DATE(YEAR(C74),MONTH(C74),1) -> 44682
A75: ORD-20074 | B75: CUST-5009 | C75: 45005 | D75: Beauty | E75: Lip Balm Set | F75: 14.99 | G75: 4 | H75: 20 | I75: 11.99 | J75: 47.96 | K75: Wallet | L75: Delivered | M75: 4 | N75: =VLOOKUP(B75,Customers!A:J,7,0) -> 54 | O75: =VLOOKUP(B75,Customers!A:J,5,0) -> Philadelphia | P75: =VLOOKUP(B75,Customers!A:J,10,0) -> Silver | Q75: =VLOOKUP(B75,Customers!A:J,8,0) -> Female | R75: =ISNUMBER(C75) -> TRUE | S75: =DATE(YEAR(C75),MONTH(C75),1) -> 44986
A76: ORD-20075 | B76: CUST-5009 | C76: 45020 | D76: Toys | E76: Action Figure | F76: 19.99 | G76: 1 | H76: 15 | I76: 16.99 | J76: 16.99 | K76: UPI | L76: Delivered | M76: 4 | N76: =VLOOKUP(B76,Customers!A:J,7,0) -> 54 | O76: =VLOOKUP(B76,Customers!A:J,5,0) -> Philadelphia | P76: =VLOOKUP(B76,Customers!A:J,10,0) -> Silver | Q76: =VLOOKUP(B76,Customers!A:J,8,0) -> Female | R76: =ISNUMBER(C76) -> TRUE | S76: =DATE(YEAR(C76),MONTH(C76),1) -> 45017
A77: ORD-20076 | B77: CUST-5009 | C77: 45311 | D77: Toys | E77: Remote Control Car | F77: 39.99 | G77: 4 | H77: 20 | I77: 31.99 | J77: 127.96 | K77: UPI | L77: Shipped | M77: 5 | N77: =VLOOKUP(B77,Customers!A:J,7,0) -> 54 | O77: =VLOOKUP(B77,Customers!A:J,5,0) -> Philadelphia | P77: =VLOOKUP(B77,Customers!A:J,10,0) -> Silver | Q77: =VLOOKUP(B77,Customers!A:J,8,0) -> Female | R77: =ISNUMBER(C77) -> TRUE | S77: =DATE(YEAR(C77),MONTH(C77),1) -> 45292
A78: ORD-20077 | B78: CUST-5009 | C78: 45099 | D78: Home & Kitchen | E78: Blender | F78: 64.99 | G78: 1 | H78: 0 | I78: 64.99 | J78: 64.99 | K78: PayPal | L78: Returned | M78: 4 | N78: =VLOOKUP(B78,Customers!A:J,7,0) -> 54 | O78: =VLOOKUP(B78,Customers!A:J,5,0) -> Philadelphia | P78: =VLOOKUP(B78,Customers!A:J,10,0) -> Silver | Q78: =VLOOKUP(B78,Customers!A:J,8,0) -> Female | R78: =ISNUMBER(C78) -> TRUE | S78: =DATE(YEAR(C78),MONTH(C78),1) -> 45078
A79: ORD-20078 | B79: CUST-5009 | C79: 44605 | D79: Beauty | E79: Hair Mask | F79: 24.99 | G79: 2 | H79: 0 | I79: 24.99 | J79: 49.98 | K79: UPI | L79: Delivered | M79: 5 | N79: =VLOOKUP(B79,Customers!A:J,7,0) -> 54 | O79: =VLOOKUP(B79,Customers!A:J,5,0) -> Philadelphia | P79: =VLOOKUP(B79,Customers!A:J,10,0) -> Silver | Q79: =VLOOKUP(B79,Customers!A:J,8,0) -> Female | R79: =ISNUMBER(C79) -> TRUE | S79: =DATE(YEAR(C79),MONTH(C79),1) -> 44593
A80: ORD-20079 | B80: CUST-5009 | C80: 45131 | D80: Toys | E80: LEGO Classic Set | F80: 49.99 | G80: 3 | H80: 0 | I80: 49.99 | J80: 149.97 | K80: Wallet | L80: Delivered | M80: 5 | N80: =VLOOKUP(B80,Customers!A:J,7,0) -> 54 | O80: =VLOOKUP(B80,Customers!A:J,5,0) -> Philadelphia | P80: =VLOOKUP(B80,Customers!A:J,10,0) -> Silver | Q80: =VLOOKUP(B80,Customers!A:J,8,0) -> Female | R80: =ISNUMBER(C80) -> TRUE | S80: =DATE(YEAR(C80),MONTH(C80),1) -> 45108
A81: ORD-20080 | B81: CUST-5009 | C81: 45104 | D81: Electronics | E81: USB-C Hub | F81: 34.99 | G81: 2 | H81: 0 | I81: 34.99 | J81: 69.98 | K81: PayPal | L81: Delivered | M81: 3 | N81: =VLOOKUP(B81,Customers!A:J,7,0) -> 54 | O81: =VLOOKUP(B81,Customers!A:J,5,0) -> Philadelphia | P81: =VLOOKUP(B81,Customers!A:J,10,0) -> Silver | Q81: =VLOOKUP(B81,Customers!A:J,8,0) -> Female | R81: =ISNUMBER(C81) -> TRUE | S81: =DATE(YEAR(C81),MONTH(C81),1) -> 45078
A82: ORD-20081 | B82: CUST-5009 | C82: 44664 | D82: Home & Kitchen | E82: Coffee Maker | F82: 59.99 | G82: 1 | H82: 15 | I82: 50.99 | J82: 50.99 | K82: Wallet | L82: Delivered | M82: 4 | N82: =VLOOKUP(B82,Customers!A:J,7,0) -> 54 | O82: =VLOOKUP(B82,Customers!A:J,5,0) -> Philadelphia | P82: =VLOOKUP(B82,Customers!A:J,10,0) -> Silver | Q82: =VLOOKUP(B82,Customers!A:J,8,0) -> Female | R82: =ISNUMBER(C82) -> TRUE | S82: =DATE(YEAR(C82),MONTH(C82),1) -> 44652
A83: ORD-20082 | B83: CUST-5009 | C83: 45613 | D83: Beauty | E83: Hair Mask | F83: 24.99 | G83: 3 | H83: 20 | I83: 19.99 | J83: 59.97 | K83: UPI | L83: Delivered | M83: 5 | N83: =VLOOKUP(B83,Customers!A:J,7,0) -> 54 | O83: =VLOOKUP(B83,Customers!A:J,5,0) -> Philadelphia | P83: =VLOOKUP(B83,Customers!A:J,10,0) -> Silver | Q83: =VLOOKUP(B83,Customers!A:J,8,0) -> Female | R83: =ISNUMBER(C83) -> TRUE | S83: =DATE(YEAR(C83),MONTH(C83),1) -> 45597
A84: ORD-20083 | B84: CUST-5009 | C84: 45018 | D84: Home & Kitchen | E84: Air Fryer | F84: 89.99 | G84: 3 | H84: 5 | I84: 85.49 | J84: 256.47 | K84: UPI | L84: Delivered | M84: 5 | N84: =VLOOKUP(B84,Customers!A:J,7,0) -> 54 | O84: =VLOOKUP(B84,Customers!A:J,5,0) -> Philadelphia | P84: =VLOOKUP(B84,Customers!A:J,10,0) -> Silver | Q84: =VLOOKUP(B84,Customers!A:J,8,0) -> Female | R84: =ISNUMBER(C84) -> TRUE | S84: =DATE(YEAR(C84),MONTH(C84),1) -> 45017
A85: ORD-20084 | B85: CUST-5009 | C85: 45491 | D85: Clothing | E85: Running Shoes | F85: 89.99 | G85: 3 | H85: 5 | I85: 85.49 | J85: 256.47 | K85: PayPal | L85: Delivered | M85: 5 | N85: =VLOOKUP(B85,Customers!A:J,7,0) -> 54 | O85: =VLOOKUP(B85,Customers!A:J,5,0) -> Philadelphia | P85: =VLOOKUP(B85,Customers!A:J,10,0) -> Silver | Q85: =VLOOKUP(B85,Customers!A:J,8,0) -> Female | R85: =ISNUMBER(C85) -> TRUE | S85: =DATE(YEAR(C85),MONTH(C85),1) -> 45474
A86: ORD-20085 | B86: CUST-5009 | C86: 44914 | D86: Books | E86: Business Analytics | F86: 39.99 | G86: 4 | H86: 0 | I86: 39.99 | J86: 159.96 | K86: Credit Card | L86: Delivered | N86: =VLOOKUP(B86,Customers!A:J,7,0) -> 54 | O86: =VLOOKUP(B86,Customers!A:J,5,0) -> Philadelphia | P86: =VLOOKUP(B86,Customers!A:J,10,0) -> Silver | Q86: =VLOOKUP(B86,Customers!A:J,8,0) -> Female | R86: =ISNUMBER(C86) -> TRUE | S86: =DATE(YEAR(C86),MONTH(C86),1) -> 44896
A87: ORD-20086 | B87: CUST-5009 | C87: 45424 | D87: Electronics | E87: Smart Watch | F87: 199.99 | G87: 4 | H87: 10 | I87: 179.99 | J87: 719.96 | K87: Debit Card | L87: Delivered | M87: 4 | N87: =VLOOKUP(B87,Customers!A:J,7,0) -> 54 | O87: =VLOOKUP(B87,Customers!A:J,5,0) -> Philadelphia | P87: =VLOOKUP(B87,Customers!A:J,10,0) -> Silver | Q87: =VLOOKUP(B87,Customers!A:J,8,0) -> Female | R87: =ISNUMBER(C87) -> TRUE | S87: =DATE(YEAR(C87),MONTH(C87),1) -> 45413
A88: ORD-20087 | B88: CUST-5010 | C88: 44700 | D88: Books | E88: Python for Beginners | F88: 29.99 | G88: 1 | H88: 20 | I88: 23.99 | J88: 23.99 | K88: Debit Card | L88: Delivered | M88: 5 | N88: =VLOOKUP(B88,Customers!A:J,7,0) -> 23 | O88: =VLOOKUP(B88,Customers!A:J,5,0) -> Jacksonville | P88: =VLOOKUP(B88,Customers!A:J,10,0) -> Free | Q88: =VLOOKUP(B88,Customers!A:J,8,0) -> Male | R88: =ISNUMBER(C88) -> TRUE | S88: =DATE(YEAR(C88),MONTH(C88),1) -> 44682
A89: ORD-20088 | B89: CUST-5010 | C89: 45578 | D89: Home & Kitchen | E89: Air Fryer | F89: 89.99 | G89: 3 | H89: 0 | I89: 89.99 | J89: 269.97 | K89: PayPal | L89: Delivered | M89: 3 | N89: =VLOOKUP(B89,Customers!A:J,7,0) -> 23 | O89: =VLOOKUP(B89,Customers!A:J,5,0) -> Jacksonville | P89: =VLOOKUP(B89,Customers!A:J,10,0) -> Free | Q89: =VLOOKUP(B89,Customers!A:J,8,0) -> Male | R89: =ISNUMBER(C89) -> TRUE | S89: =DATE(YEAR(C89),MONTH(C89),1) -> 45566
A90: ORD-20089 | B90: CUST-5010 | C90: 44835 | D90: Electronics | E90: Bluetooth Speaker | F90: 49.99 | G90: 2 | H90: 5 | I90: 47.49 | J90: 94.98 | K90: UPI | L90: Delivered | M90: 2 | N90: =VLOOKUP(B90,Customers!A:J,7,0) -> 23 | O90: =VLOOKUP(B90,Customers!A:J,5,0) -> Jacksonville | P90: =VLOOKUP(B90,Customers!A:J,10,0) -> Free | Q90: =VLOOKUP(B90,Customers!A:J,8,0) -> Male | R90: =ISNUMBER(C90) -> TRUE | S90: =DATE(YEAR(C90),MONTH(C90),1) -> 44835
A91: ORD-20090 | B91: CUST-5010 | C91: 45063 | D91: Beauty | E91: Moisturizer SPF 50 | F91: 29.99 | G91: 3 | H91: 0 | I91: 29.99 | J91: 89.97 | K91: PayPal | L91: Delivered | M91: 3 | N91: =VLOOKUP(B91,Customers!A:J,7,0) -> 23 | O91: =VLOOKUP(B91,Customers!A:J,5,0) -> Jacksonville | P91: =VLOOKUP(B91,Customers!A:J,10,0) -> Free | Q91: =VLOOKUP(B91,Customers!A:J,8,0) -> Male | R91: =ISNUMBER(C91) -> TRUE | S91: =DATE(YEAR(C91),MONTH(C91),1) -> 45047
A92: ORD-20091 | B92: CUST-5010 | C92: 44942 | D92: Toys | E92: Action Figure | F92: 19.99 | G92: 2 | H92: 5 | I92: 18.99 | J92: 37.98 | K92: PayPal | L92: Delivered | M92: 4 | N92: =VLOOKUP(B92,Customers!A:J,7,0) -> 23 | O92: =VLOOKUP(B92,Customers!A:J,5,0) -> Jacksonville | P92: =VLOOKUP(B92,Customers!A:J,10,0) -> Free | Q92: =VLOOKUP(B92,Customers!A:J,8,0) -> Male | R92: =ISNUMBER(C92) -> TRUE | S92: =DATE(YEAR(C92),MONTH(C92),1) -> 44927
A93: ORD-20092 | B93: CUST-5010 | C93: 45061 | D93: Toys | E93: Action Figure | F93: 19.99 | G93: 4 | H93: 10 | I93: 17.99 | J93: 71.96 | K93: PayPal | L93: Delivered | M93: 5 | N93: =VLOOKUP(B93,Customers!A:J,7,0) -> 23 | O93: =VLOOKUP(B93,Customers!A:J,5,0) -> Jacksonville | P93: =VLOOKUP(B93,Customers!A:J,10,0) -> Free | Q93: =VLOOKUP(B93,Customers!A:J,8,0) -> Male | R93: =ISNUMBER(C93) -> TRUE | S93: =DATE(YEAR(C93),MONTH(C93),1) -> 45047
A94: ORD-20093 | B94: CUST-5011 | C94: 45553 | D94: Beauty | E94: Moisturizer SPF 50 | F94: 29.99 | G94: 2 | H94: 5 | I94: 28.49 | J94: 56.98 | K94: Credit Card | L94: Delivered | M94: 4 | N94: =VLOOKUP(B94,Customers!A:J,7,0) -> 48 | O94: =VLOOKUP(B94,Customers!A:J,5,0) -> Philadelphia | P94: =VLOOKUP(B94,Customers!A:J,10,0) -> Gold | Q94: =VLOOKUP(B94,Customers!A:J,8,0) -> Male | R94: =ISNUMBER(C94) -> TRUE | S94: =DATE(YEAR(C94),MONTH(C94),1) -> 45536
A95: ORD-20094 | B95: CUST-5011 | C95: 45635 | D95: Beauty | E95: Moisturizer SPF 50 | F95: 29.99 | G95: 3 | H95: 0 | I95: 29.99 | J95: 89.97 | K95: PayPal | L95: Delivered | M95: 3 | N95: =VLOOKUP(B95,Customers!A:J,7,0) -> 48 | O95: =VLOOKUP(B95,Customers!A:J,5,0) -> Philadelphia | P95: =VLOOKUP(B95,Customers!A:J,10,0) -> Gold | Q95: =VLOOKUP(B95,Customers!A:J,8,0) -> Male | R95: =ISNUMBER(C95) -> TRUE | S95: =DATE(YEAR(C95),MONTH(C95),1) -> 45627
A96: ORD-20095 | B96: CUST-5011 | C96: 45189 | D96: Home & Kitchen | E96: Non-stick Pan Set | F96: 44.99 | G96: 2 | H96: 15 | I96: 38.24 | J96: 76.48 | K96: PayPal | L96: Delivered | M96: 3 | N96: =VLOOKUP(B96,Customers!A:J,7,0) -> 48 | O96: =VLOOKUP(B96,Customers!A:J,5,0) -> Philadelphia | P96: =VLOOKUP(B96,Customers!A:J,10,0) -> Gold | Q96: =VLOOKUP(B96,Customers!A:J,8,0) -> Male | R96: =ISNUMBER(C96) -> TRUE | S96: =DATE(YEAR(C96),MONTH(C96),1) -> 45170
A97: ORD-20096 | B97: CUST-5011 | C97: 44756 | D97: Sports | E97: Water Bottle | F97: 24.99 | G97: 3 | H97: 20 | I97: 19.99 | J97: 59.97 | K97: Wallet | L97: Delivered | M97: 3 | N97: =VLOOKUP(B97,Customers!A:J,7,0) -> 48 | O97: =VLOOKUP(B97,Customers!A:J,5,0) -> Philadelphia | P97: =VLOOKUP(B97,Customers!A:J,10,0) -> Gold | Q97: =VLOOKUP(B97,Customers!A:J,8,0) -> Male | R97: =ISNUMBER(C97) -> TRUE | S97: =DATE(YEAR(C97),MONTH(C97),1) -> 44743
A98: ORD-20097 | B98: CUST-5012 | C98: 45128 | D98: Sports | E98: Yoga Mat | F98: 29.99 | G98: 2 | H98: 10 | I98: 26.99 | J98: 53.98 | K98: Wallet | L98: Delivered | M98: 4 | N98: =VLOOKUP(B98,Customers!A:J,7,0) -> 25 | O98: =VLOOKUP(B98,Customers!A:J,5,0) -> New York | P98: =VLOOKUP(B98,Customers!A:J,10,0) -> Free | Q98: =VLOOKUP(B98,Customers!A:J,8,0) -> Female | R98: =ISNUMBER(C98) -> TRUE | S98: =DATE(YEAR(C98),MONTH(C98),1) -> 45108
... A102: ORD-20101 | B102: CUST-5012 | C102: 44779 | D102: Home & Kitchen | E102: Non-stick Pan Set | F102: 44.99 | G102: 3 | H102: 0 | I102: 44.99 | J102: 134.97 | K102: UPI | L102: Delivered | M102: 5 | N102: =VLOOKUP(B102,Customers!A:J,7,0) -> 25 | O102: =VLOOKUP(B102,Customers!A:J,5,0) -> New York | P102: =VLOOKUP(B102,Customers!A:J,10,0) -> Free | Q102: =VLOOKUP(B102,Customers!A:J,8,0) -> Female | R102: =ISNUMBER(C102) -> TRUE | S102: =DATE(YEAR(C102),MONTH(C102),1) -> 44774
A103: ORD-20102 | B103: CUST-5012 | C103: 45197 | D103: Clothing | E103: Denim Jacket | F103: 69.99 | G103: 1 | H103: 0 | I103: 69.99 | J103: 69.99 | K103: Wallet | L103: Delivered | N103: =VLOOKUP(B103,Customers!A:J,7,0) -> 25 | O103: =VLOOKUP(B103,Customers!A:J,5,0) -> New York | P103: =VLOOKUP(B103,Customers!A:J,10,0) -> Free | Q103: =VLOOKUP(B103,Customers!A:J,8,0) -> Female | R103: =ISNUMBER(C103) -> TRUE | S103: =DATE(YEAR(C103),MONTH(C103),1) -> 45170
...

Sheet Pivot_Analysis
A1: rati | B1: Sum of order_total | C1: Count of order_id | D1: Average of rating | H1: Row Labels | I1: Sum of order_total | J1: Average of order_total2
A2: Electronics | B2: 46884.23 | C2: 225 | D2: 4.0066667 | H2: Free | I2: 91517.53 | J2: 109.73325
A3: Home & Kitchen | B3: 36312.97 | C3: 236 | D3: 4.0584795 | H3: Silver | I3: 50255.37 | J3: 104.26425
A4: Clothing | B4: 31322.64 | C4: 261 | D4: 4.0617978 | H4: Platinum | I4: 20797 | J4: 110.03704
A5: Toys | B5: 20328.98 | C5: 249 | D5: 4.1412429 | H5: Gold | I5: 16690.65 | J5: 112.01779
A6: Books | B6: 18687.63 | C6: 233 | D6: 4.2012195 | H6: Grand Total | I6: 179260.55 | J6: 108.38002
A7: Beauty | B7: 14108.7 | C7: 226 | D7: 4.1401274
A8: Sports | B8: 11615.4 | C8: 224 | D8: 4.054878
A9: Grand Total | B9: 179260.55 | C9: 1654 | D9: 4.0956072
B12: Total Revenue
A13: Row Labels | B13: Sum of order_total | C13: Count of order_id | F13: Row Labels | G13: Sum of order_total
A14: Delivered | B14: 154704.02 | C14: 1419 | F14: 2022 | G14: 62142.83
A15: Shipped | B15: 9942.93 | C15: 108 | F15: 2023 | G15: 58744.36
A16: Processing | B16: 8044.54 | C16: 64 | F16: 2024 | G16: 58373.36
A17: Returned | B17: 3440.76 | C17: 32 | F17: Grand Total | G17: 179260.55
A18: Cancelled | B18: 3128.3 | C18: 31
A19: Grand Total | B19: 179260.55 | C19: 1654
A22: Total Revenue | B22: Total Orders | C22: Avg Order Value | D22: Return Rate | E22: Top Category
A23: =SUMIF(Orders!L:L,"Delivered",Orders!J:J) -> 154704.02 | B23: =COUNTIF(Orders!L:L,"Delivered") -> 1419 | C23: =SUMIF(Orders!L:L,"Delivered",Orders!J:J)/COUNTIF(Orders!L:L,"Delivered") -> 109.02327 | D23: =COUNTIF(Orders!L:L,"Returned")/(COUNTA(Orders!A:A)-1)*100 -> 1.9347037 | E23: =INDEX(A2:A8,MATCH(MAX(B2:B8),B2:B8,0)) -> Electronics

Sheet Analysis_Guide
A1: Analysis Tasks for This Project
A3: 1. Customer Segmentation | B3: Segment customers by membership tier and analyze AOV, frequency
A4: 2. Cohort Retention | B4: Group customers by join quarter; track repeat purchase rates
A5: 3. Category Performance | B5: Revenue, units sold, avg discount, and return rate by category
A6: 4. Payment Method Trends | B6: Preferred payment by age group and membership tier
A7: 5. Rating vs Revenue | B7: Correlation between product ratings and repeat purchases
A8: 6. RFM Analysis | B8: Recency, Frequency, Monetary segmentation using SQL or Excel
A9: 7. Top Cities Dashboard | B9: Revenue by city on a Tableau map visualization
